[
  {
    "id": "qianqiu-wansui-1985-09-23-001-obwfeokf5hlmfiefk0fgo",
    "date": "1985-09-23",
    "displayDate": "1985年9月23日晨7时半",
    "datePrecision": "day",
    "title": "李敖写《第一条多了什么？》",
    "summary": "《第一条多了什么？》署1985年9月23日晨7时半。李敖在这篇文字中延续《千秋万岁乌鸦求是合集》的政论、读书札记或杂文写作脉络，留下一个可定位的写作节点。",
    "view": [
      "写作线"
    ],
    "tags": [
      "千秋万岁乌鸦求是合集",
      "第一条多了什么？",
      "1985"
    ],
    "people": [
      "李敖"
    ],
    "places": [
      "台湾"
    ],
    "works": [
      "千秋万岁乌鸦求是合集",
      "第一条多了什么？"
    ],
    "certainty": "confirmed",
    "source": {
      "book": "千秋万岁乌鸦求是合集",
      "chapter": "001.第一条多了什么？",
      "path": "《大李敖全集5.0》（wjm_tcy版）分章节/003.惊世杂文类/013.千秋万岁乌鸦求是合集/001.第一条多了什么？.txt",
      "line": 31
    }
  },
  {
    "id": "qianqiu-wansui-1985-03-02-002-ffufjuqx8fga-inqgk1n9j",
    "date": "1985-03-02",
    "displayDate": "1985年3月2日",
    "datePrecision": "day",
    "title": "李敖写《“个人行为”并发症》",
    "summary": "《“个人行为”并发症》署1985年3月2日。李敖在这篇文字中延续《千秋万岁乌鸦求是合集》的政论、读书札记或杂文写作脉络，留下一个可定位的写作节点。",
    "view": [
      "写作线"
    ],
    "tags": [
      "千秋万岁乌鸦求是合集",
      "“个人行为”并发症",
      "1985"
    ],
    "people": [
      "李敖"
    ],
    "places": [
      "台湾"
    ],
    "works": [
      "千秋万岁乌鸦求是合集",
      "“个人行为”并发症"
    ],
    "certainty": "confirmed",
    "source": {
      "book": "千秋万岁乌鸦求是合集",
      "chapter": "002.“个人行为”并发症",
      "path": "《大李敖全集5.0》（wjm_tcy版）分章节/003.惊世杂文类/013.千秋万岁乌鸦求是合集/002.“个人行为”并发症.txt",
      "line": 55
    }
  },
  {
    "id": "qianqiu-wansui-1985-09-23-003-fexlchfgbfgpgkjhmco05",
    "date": "1985-09-23",
    "displayDate": "1985年9月23日晨3时半到6时",
    "datePrecision": "day",
    "title": "李敖写《三民主义口头禅》",
    "summary": "《三民主义口头禅》署1985年9月23日晨3时半到6时。李敖在这篇文字中延续《千秋万岁乌鸦求是合集》的政论、读书札记或杂文写作脉络，留下一个可定位的写作节点。",
    "view": [
      "写作线"
    ],
    "tags": [
      "千秋万岁乌鸦求是合集",
      "三民主义口头禅",
      "1985"
    ],
    "people": [
      "李敖"
    ],
    "places": [
      "台湾"
    ],
    "works": [
      "千秋万岁乌鸦求是合集",
      "三民主义口头禅"
    ],
    "certainty": "confirmed",
    "source": {
      "book": "千秋万岁乌鸦求是合集",
      "chapter": "003.三民主义口头禅",
      "path": "《大李敖全集5.0》（wjm_tcy版）分章节/003.惊世杂文类/013.千秋万岁乌鸦求是合集/003.三民主义口头禅.txt",
      "line": 31
    }
  },
  {
    "id": "qianqiu-wansui-1985-11-24-004-hqjnolnj3jzyh7son2iwe",
    "date": "1985-11-24",
    "displayDate": "1985年11月24日夜，病中作",
    "datePrecision": "day",
    "title": "李敖写《始知真放在精微》",
    "summary": "《始知真放在精微》署1985年11月24日夜，病中作。李敖在这篇文字中延续《千秋万岁乌鸦求是合集》的政论、读书札记或杂文写作脉络，留下一个可定位的写作节点。",
    "view": [
      "写作线"
    ],
    "tags": [
      "千秋万岁乌鸦求是合集",
      "始知真放在精微",
      "1985"
    ],
    "people": [
      "李敖"
    ],
    "places": [
      "台湾"
    ],
    "works": [
      "千秋万岁乌鸦求是合集",
      "始知真放在精微"
    ],
    "certainty": "confirmed",
    "source": {
      "book": "千秋万岁乌鸦求是合集",
      "chapter": "004.始知真放在精微",
      "path": "《大李敖全集5.0》（wjm_tcy版）分章节/003.惊世杂文类/013.千秋万岁乌鸦求是合集/004.始知真放在精微.txt",
      "line": 29
    }
  },
  {
    "id": "qianqiu-wansui-1985-03-23-005-sexgkrfk0fgog30irki3lg84-kemk0m-gkysgq",
    "date": "1985-03-23",
    "displayDate": "1985年3月23日",
    "datePrecision": "day",
    "title": "李敖与史通写《这叫什么公开审判？》",
    "summary": "《这叫什么公开审判？（李敖·史通）》署1985年3月23日。李敖在这篇文字中延续《千秋万岁乌鸦求是合集》的政论、读书札记或杂文写作脉络，留下一个可定位的写作节点。",
    "view": [
      "写作线",
      "法律线"
    ],
    "tags": [
      "千秋万岁乌鸦求是合集",
      "这叫什么公开审判？（李敖·史通）",
      "1985",
      "江南案"
    ],
    "people": [
      "李敖",
      "史通",
      "汪希苓",
      "陈启礼",
      "刘宜良"
    ],
    "places": [
      "台湾"
    ],
    "works": [
      "千秋万岁乌鸦求是合集",
      "这叫什么公开审判？（李敖·史通）"
    ],
    "certainty": "confirmed",
    "source": {
      "book": "千秋万岁乌鸦求是合集",
      "chapter": "005.这叫什么公开审判？（李敖·史通）",
      "path": "《大李敖全集5.0》（wjm_tcy版）分章节/003.惊世杂文类/013.千秋万岁乌鸦求是合集/005.这叫什么公开审判？（李敖·史通）.txt",
      "line": 89
    }
  },
  {
    "id": "qianqiu-wansui-1985-04-26-006-l7nfgpi7lfgafoggk1fji",
    "date": "1985-04-26",
    "displayDate": "1985年4月26日晨",
    "datePrecision": "day",
    "title": "李敖写《正义就为你发亮》",
    "summary": "《正义就为你发亮》署1985年4月26日晨。李敖在这篇文字中延续《千秋万岁乌鸦求是合集》的政论、读书札记或杂文写作脉络，留下一个可定位的写作节点。",
    "view": [
      "写作线"
    ],
    "tags": [
      "千秋万岁乌鸦求是合集",
      "正义就为你发亮",
      "1985"
    ],
    "people": [
      "李敖"
    ],
    "places": [
      "台湾"
    ],
    "works": [
      "千秋万岁乌鸦求是合集",
      "正义就为你发亮"
    ],
    "certainty": "confirmed",
    "source": {
      "book": "千秋万岁乌鸦求是合集",
      "chapter": "006.正义就为你发亮",
      "path": "《大李敖全集5.0》（wjm_tcy版）分章节/003.惊世杂文类/013.千秋万岁乌鸦求是合集/006.正义就为你发亮.txt",
      "line": 37
    }
  },
  {
    "id": "qianqiu-wansui-1989-03-06-008-k1zgeuo25mqy-jolo25rlc",
    "date": "1989-03-06",
    "displayDate": "1989年3月6日",
    "datePrecision": "day",
    "title": "李敖写《“文化种猪”接种记》",
    "summary": "《“文化种猪”接种记》署1989年3月6日。李敖在这篇文字中延续《千秋万岁乌鸦求是合集》的政论、读书札记或杂文写作脉络，留下一个可定位的写作节点。",
    "view": [
      "写作线"
    ],
    "tags": [
      "千秋万岁乌鸦求是合集",
      "“文化种猪”接种记",
      "1989"
    ],
    "people": [
      "李敖"
    ],
    "places": [
      "台湾"
    ],
    "works": [
      "千秋万岁乌鸦求是合集",
      "“文化种猪”接种记"
    ],
    "certainty": "confirmed",
    "source": {
      "book": "千秋万岁乌鸦求是合集",
      "chapter": "008.“文化种猪”接种记",
      "path": "《大李敖全集5.0》（wjm_tcy版）分章节/003.惊世杂文类/013.千秋万岁乌鸦求是合集/008.“文化种猪”接种记.txt",
      "line": 13
    }
  },
  {
    "id": "qianqiu-wansui-1983-04-03-009-ff1h5qkf9ff2h5qff1kf9",
    "date": "1983-04-03",
    "displayDate": "1983年4月3日",
    "datePrecision": "day",
    "title": "李敖写《不回来与回不来》",
    "summary": "《不回来与回不来》署1983年4月3日。李敖在这篇文字中延续《千秋万岁乌鸦求是合集》的政论、读书札记或杂文写作脉络，留下一个可定位的写作节点。",
    "view": [
      "写作线"
    ],
    "tags": [
      "千秋万岁乌鸦求是合集",
      "不回来与回不来",
      "1983"
    ],
    "people": [
      "李敖"
    ],
    "places": [
      "台湾"
    ],
    "works": [
      "千秋万岁乌鸦求是合集",
      "不回来与回不来"
    ],
    "certainty": "confirmed",
    "source": {
      "book": "千秋万岁乌鸦求是合集",
      "chapter": "009.不回来与回不来",
      "path": "《大李敖全集5.0》（wjm_tcy版）分章节/003.惊世杂文类/013.千秋万岁乌鸦求是合集/009.不回来与回不来.txt",
      "line": 77
    }
  },
  {
    "id": "qianqiu-wansui-1983-07-28-011-h7siovhi7ffxq3pire",
    "date": "1983-07-28",
    "displayDate": "1983年7月28日",
    "datePrecision": "day",
    "title": "李敖写《在废墟中营建》",
    "summary": "《在废墟中营建》署1983年7月28日。李敖在这篇文字中延续《千秋万岁乌鸦求是合集》的政论、读书札记或杂文写作脉络，留下一个可定位的写作节点。",
    "view": [
      "写作线"
    ],
    "tags": [
      "千秋万岁乌鸦求是合集",
      "在废墟中营建",
      "1983"
    ],
    "people": [
      "李敖"
    ],
    "places": [
      "台湾"
    ],
    "works": [
      "千秋万岁乌鸦求是合集",
      "在废墟中营建"
    ],
    "certainty": "confirmed",
    "source": {
      "book": "千秋万岁乌鸦求是合集",
      "chapter": "011.在废墟中营建",
      "path": "《大李敖全集5.0》（wjm_tcy版）分章节/003.惊世杂文类/013.千秋万岁乌鸦求是合集/011.在废墟中营建.txt",
      "line": 177
    }
  },
  {
    "id": "qianqiu-wansui-1983-07-07-013-lrspybfozpnuuc6nesfjukebj67fgp",
    "date": "1983-07-07",
    "displayDate": "1983年7月7日",
    "datePrecision": "day",
    "title": "李敖写《游荣佳自首的人权意义》",
    "summary": "《游荣佳自首的人权意义》署1983年7月7日。李敖在这篇文字中延续《千秋万岁乌鸦求是合集》的政论、读书札记或杂文写作脉络，留下一个可定位的写作节点。",
    "view": [
      "写作线"
    ],
    "tags": [
      "千秋万岁乌鸦求是合集",
      "游荣佳自首的人权意义",
      "1983"
    ],
    "people": [
      "李敖"
    ],
    "places": [
      "台湾"
    ],
    "works": [
      "千秋万岁乌鸦求是合集",
      "游荣佳自首的人权意义"
    ],
    "certainty": "confirmed",
    "source": {
      "book": "千秋万岁乌鸦求是合集",
      "chapter": "013.游荣佳自首的人权意义",
      "path": "《大李敖全集5.0》（wjm_tcy版）分章节/003.惊世杂文类/013.千秋万岁乌鸦求是合集/013.游荣佳自首的人权意义.txt",
      "line": 33
    }
  },
  {
    "id": "qianqiu-wansui-1987-07-17-017-feouc6u4kr9crmf",
    "date": "1987-07-17",
    "displayDate": "1987年7月17日",
    "datePrecision": "day",
    "title": "李敖写《一首预言诗》",
    "summary": "《一首预言诗》署1987年7月17日。李敖在这篇文字中延续《千秋万岁乌鸦求是合集》的政论、读书札记或杂文写作脉络，留下一个可定位的写作节点。",
    "view": [
      "写作线"
    ],
    "tags": [
      "千秋万岁乌鸦求是合集",
      "一首预言诗",
      "1987"
    ],
    "people": [
      "李敖"
    ],
    "places": [
      "台湾"
    ],
    "works": [
      "千秋万岁乌鸦求是合集",
      "一首预言诗"
    ],
    "certainty": "confirmed",
    "source": {
      "book": "千秋万岁乌鸦求是合集",
      "chapter": "017.一首预言诗",
      "path": "《大李敖全集5.0》（wjm_tcy版）分章节/003.惊世杂文类/013.千秋万岁乌鸦求是合集/017.一首预言诗.txt",
      "line": 45
    }
  },
  {
    "id": "qianqiu-wansui-1970-10-15-018-mk8mk8-jdd-k1zi1y",
    "date": "1970-10-15",
    "displayDate": "1970年10月15日原载《文坛》第二五六期",
    "datePrecision": "day",
    "title": "《爸爸·我·文学》原载《文坛》",
    "summary": "《爸爸·我·文学》文末标明原载1970年10月15日《文坛》第二五六期。这一条作为李敖该文公开发表的作品史节点入库。",
    "view": [
      "发表线",
      "家庭线",
      "写作线"
    ],
    "tags": [
      "千秋万岁乌鸦求是合集",
      "爸爸·我·文学",
      "1970"
    ],
    "people": [
      "李敖"
    ],
    "places": [
      "台湾"
    ],
    "works": [
      "千秋万岁乌鸦求是合集",
      "爸爸·我·文学",
      "文坛"
    ],
    "certainty": "confirmed",
    "source": {
      "book": "千秋万岁乌鸦求是合集",
      "chapter": "018.爸爸·我·文学",
      "path": "《大李敖全集5.0》（wjm_tcy版）分章节/003.惊世杂文类/013.千秋万岁乌鸦求是合集/018.爸爸·我·文学.txt",
      "line": 199
    }
  },
  {
    "id": "qianqiu-wansui-1981-07-22-019-izhj5fff1gk8-sp9twpgotglz",
    "date": "1981-07-22",
    "displayDate": "1981年7月22日重写",
    "datePrecision": "day",
    "title": "李敖重写《思想不变，配革命吗？》",
    "summary": "《思想不变，配革命吗？》文末署1981年7月22日重写，显示李敖在出狱前后对革命、思想与政治立场旧题的再处理。",
    "view": [
      "写作线"
    ],
    "tags": [
      "千秋万岁乌鸦求是合集",
      "思想不变，配革命吗？",
      "1981",
      "重写"
    ],
    "people": [
      "李敖"
    ],
    "places": [
      "台湾"
    ],
    "works": [
      "千秋万岁乌鸦求是合集",
      "思想不变，配革命吗？"
    ],
    "certainty": "confirmed",
    "source": {
      "book": "千秋万岁乌鸦求是合集",
      "chapter": "019.思想不变，配革命吗？",
      "path": "《大李敖全集5.0》（wjm_tcy版）分章节/003.惊世杂文类/013.千秋万岁乌鸦求是合集/019.思想不变，配革命吗？.txt",
      "line": 99
    }
  },
  {
    "id": "qianqiu-wansui-1981-07-22-020-kcpg37lchkebnesfeoffuk05fij",
    "date": "1981-07-22",
    "displayDate": "1981年7月22日",
    "datePrecision": "day",
    "title": "李敖写《有关民权的一个故事》",
    "summary": "《有关民权的一个故事》署1981年7月22日。李敖在这篇文字中延续《千秋万岁乌鸦求是合集》的政论、读书札记或杂文写作脉络，留下一个可定位的写作节点。",
    "view": [
      "写作线"
    ],
    "tags": [
      "千秋万岁乌鸦求是合集",
      "有关民权的一个故事",
      "1981"
    ],
    "people": [
      "李敖"
    ],
    "places": [
      "台湾"
    ],
    "works": [
      "千秋万岁乌鸦求是合集",
      "有关民权的一个故事"
    ],
    "certainty": "confirmed",
    "source": {
      "book": "千秋万岁乌鸦求是合集",
      "chapter": "020.有关民权的一个故事",
      "path": "《大李敖全集5.0》（wjm_tcy版）分章节/003.惊世杂文类/013.千秋万岁乌鸦求是合集/020.有关民权的一个故事.txt",
      "line": 9
    }
  },
  {
    "id": "qianqiu-wansui-1980-11-23-023-h6mfhiubqi1yff1oevfk0fgoi1y",
    "date": "1980-11-23",
    "displayDate": "1980年11月23日",
    "datePrecision": "day",
    "title": "李敖写《图书馆学不算什么学》",
    "summary": "《图书馆学不算什么学》署1980年11月23日。李敖在这篇文字中延续《千秋万岁乌鸦求是合集》的政论、读书札记或杂文写作脉络，留下一个可定位的写作节点。",
    "view": [
      "写作线"
    ],
    "tags": [
      "千秋万岁乌鸦求是合集",
      "图书馆学不算什么学",
      "1980"
    ],
    "people": [
      "李敖"
    ],
    "places": [
      "台湾"
    ],
    "works": [
      "千秋万岁乌鸦求是合集",
      "图书馆学不算什么学"
    ],
    "certainty": "confirmed",
    "source": {
      "book": "千秋万岁乌鸦求是合集",
      "chapter": "023.图书馆学不算什么学",
      "path": "《大李敖全集5.0》（wjm_tcy版）分章节/003.惊世杂文类/013.千秋万岁乌鸦求是合集/023.图书馆学不算什么学.txt",
      "line": 15
    }
  },
  {
    "id": "qianqiu-wansui-1966-04-09-024-sjjnzsi1yi6noe8",
    "date": "1966-04-09",
    "displayDate": "1966年4月9日周末夜3时15分",
    "datePrecision": "day",
    "title": "李敖写《避祸学小简》",
    "summary": "《避祸学小简》署1966年4月9日周末夜3时15分。李敖在这篇文字中延续《千秋万岁乌鸦求是合集》的政论、读书札记或杂文写作脉络，留下一个可定位的写作节点。",
    "view": [
      "写作线"
    ],
    "tags": [
      "千秋万岁乌鸦求是合集",
      "避祸学小简",
      "1966"
    ],
    "people": [
      "李敖"
    ],
    "places": [
      "台湾"
    ],
    "works": [
      "千秋万岁乌鸦求是合集",
      "避祸学小简"
    ],
    "certainty": "confirmed",
    "source": {
      "book": "千秋万岁乌鸦求是合集",
      "chapter": "024.避祸学小简",
      "path": "《大李敖全集5.0》（wjm_tcy版）分章节/003.惊世杂文类/013.千秋万岁乌鸦求是合集/024.避祸学小简.txt",
      "line": 15
    }
  },
  {
    "id": "qianqiu-wansui-1982-12-31-025-pnun5dgkqga1gjwjez",
    "date": "1982-12-31",
    "displayDate": "1982年狱中作",
    "datePrecision": "year",
    "title": "李敖在狱中写《自由只剩双手》",
    "summary": "《自由只剩双手》文末标为1982年狱中作。李敖在坐牢语境下写作此文，题名本身即保留狱中自由被压缩后的身体感与写作节点。",
    "view": [
      "写作线",
      "监狱线"
    ],
    "tags": [
      "千秋万岁乌鸦求是合集",
      "自由只剩双手",
      "1982",
      "狱中作"
    ],
    "people": [
      "李敖"
    ],
    "places": [
      "土城看守所",
      "台湾"
    ],
    "works": [
      "千秋万岁乌鸦求是合集",
      "自由只剩双手"
    ],
    "certainty": "contextual",
    "source": {
      "book": "千秋万岁乌鸦求是合集",
      "chapter": "025.自由只剩双手",
      "path": "《大李敖全集5.0》（wjm_tcy版）分章节/003.惊世杂文类/013.千秋万岁乌鸦求是合集/025.自由只剩双手.txt",
      "line": 35
    }
  },
  {
    "id": "qianqiu-wansui-1982-01-05-026-h8wmlenesfexgg1fexff1fjaiy3gqx",
    "date": "1982-01-05",
    "displayDate": "1982年1月5日，狱中作",
    "datePrecision": "day",
    "title": "李敖在狱中写《坐牢的三十三不亦快哉》",
    "summary": "《坐牢的三十三不亦快哉》署1982年1月5日，狱中作。李敖在这篇文字中延续《千秋万岁乌鸦求是合集》的政论、读书札记或杂文写作脉络，留下一个可定位的写作节点。",
    "view": [
      "写作线",
      "监狱线"
    ],
    "tags": [
      "千秋万岁乌鸦求是合集",
      "坐牢的三十三不亦快哉",
      "1982",
      "狱中作"
    ],
    "people": [
      "李敖"
    ],
    "places": [
      "土城看守所",
      "台湾"
    ],
    "works": [
      "千秋万岁乌鸦求是合集",
      "坐牢的三十三不亦快哉"
    ],
    "certainty": "confirmed",
    "source": {
      "book": "千秋万岁乌鸦求是合集",
      "chapter": "026.坐牢的三十三不亦快哉",
      "path": "《大李敖全集5.0》（wjm_tcy版）分章节/003.惊世杂文类/013.千秋万岁乌鸦求是合集/026.坐牢的三十三不亦快哉.txt",
      "line": 69
    }
  },
  {
    "id": "qianqiu-wansui-1982-04-02-027-s0vpa9hm2htyke8fjujzym7f",
    "date": "1982-04-02",
    "displayDate": "1982年4月2日",
    "datePrecision": "day",
    "title": "李敖写《跟老太婆杀人放火》",
    "summary": "《跟老太婆杀人放火》署1982年4月2日。李敖在这篇文字中延续《千秋万岁乌鸦求是合集》的政论、读书札记或杂文写作脉络，留下一个可定位的写作节点。",
    "view": [
      "写作线"
    ],
    "tags": [
      "千秋万岁乌鸦求是合集",
      "跟老太婆杀人放火",
      "1982"
    ],
    "people": [
      "李敖"
    ],
    "places": [
      "台湾"
    ],
    "works": [
      "千秋万岁乌鸦求是合集",
      "跟老太婆杀人放火"
    ],
    "certainty": "confirmed",
    "source": {
      "book": "千秋万岁乌鸦求是合集",
      "chapter": "027.跟老太婆杀人放火",
      "path": "《大李敖全集5.0》（wjm_tcy版）分章节/003.惊世杂文类/013.千秋万岁乌鸦求是合集/027.跟老太婆杀人放火.txt",
      "line": 9
    }
  },
  {
    "id": "qianqiu-wansui-1982-06-11-028-lpzqmjnesjh1nzc-lpzqmjnesitvi46",
    "date": "1982-06-11",
    "displayDate": "1982年6月11日",
    "datePrecision": "day",
    "title": "李敖写《混蛋的投票·混蛋的当家》",
    "summary": "《混蛋的投票·混蛋的当家》署1982年6月11日。李敖在这篇文字中延续《千秋万岁乌鸦求是合集》的政论、读书札记或杂文写作脉络，留下一个可定位的写作节点。",
    "view": [
      "写作线"
    ],
    "tags": [
      "千秋万岁乌鸦求是合集",
      "混蛋的投票·混蛋的当家",
      "1982"
    ],
    "people": [
      "李敖"
    ],
    "places": [
      "台湾"
    ],
    "works": [
      "千秋万岁乌鸦求是合集",
      "混蛋的投票·混蛋的当家"
    ],
    "certainty": "confirmed",
    "source": {
      "book": "千秋万岁乌鸦求是合集",
      "chapter": "028.混蛋的投票·混蛋的当家",
      "path": "《大李敖全集5.0》（wjm_tcy版）分章节/003.惊世杂文类/013.千秋万岁乌鸦求是合集/028.混蛋的投票·混蛋的当家.txt",
      "line": 9
    }
  },
  {
    "id": "qianqiu-wansui-1982-06-24-029-rlmffxtm0kepfijfli",
    "date": "1982-06-24",
    "displayDate": "1982年6月24日《台湾时报》",
    "datePrecision": "day",
    "title": "《论中门村事件》刊于《台湾时报》",
    "summary": "《论中门村事件》文末标明1982年6月24日《台湾时报》。本轮按原刊日收为李敖该文公开发表节点。",
    "view": [
      "发表线",
      "政治线"
    ],
    "tags": [
      "千秋万岁乌鸦求是合集",
      "论中门村事件",
      "1982",
      "台湾时报"
    ],
    "people": [
      "李敖"
    ],
    "places": [
      "台湾"
    ],
    "works": [
      "千秋万岁乌鸦求是合集",
      "论中门村事件",
      "台湾时报"
    ],
    "certainty": "confirmed",
    "source": {
      "book": "千秋万岁乌鸦求是合集",
      "chapter": "029.论中门村事件",
      "path": "《大李敖全集5.0》（wjm_tcy版）分章节/003.惊世杂文类/013.千秋万岁乌鸦求是合集/029.论中门村事件.txt",
      "line": 133
    }
  },
  {
    "id": "qianqiu-wansui-1982-07-24-030-ghygkyglprm5gjskf9fie",
    "date": "1982-07-24",
    "displayDate": "1982年7月24日",
    "datePrecision": "day",
    "title": "李敖写《历史名词又来了！》",
    "summary": "《历史名词又来了！》署1982年7月24日。李敖在这篇文字中延续《千秋万岁乌鸦求是合集》的政论、读书札记或杂文写作脉络，留下一个可定位的写作节点。",
    "view": [
      "写作线"
    ],
    "tags": [
      "千秋万岁乌鸦求是合集",
      "历史名词又来了！",
      "1982"
    ],
    "people": [
      "李敖"
    ],
    "places": [
      "台湾"
    ],
    "works": [
      "千秋万岁乌鸦求是合集",
      "历史名词又来了！"
    ],
    "certainty": "confirmed",
    "source": {
      "book": "千秋万岁乌鸦求是合集",
      "chapter": "030.历史名词又来了！",
      "path": "《大李敖全集5.0》（wjm_tcy版）分章节/003.惊世杂文类/013.千秋万岁乌鸦求是合集/030.历史名词又来了！.txt",
      "line": 27
    }
  },
  {
    "id": "qianqiu-wansui-1982-12-05-033-ff1jf7g6zpnun5dfgbfgpglz",
    "date": "1982-12-05",
    "displayDate": "1982年12月5日",
    "datePrecision": "day",
    "title": "李敖写《不打击自由主义吗？》",
    "summary": "《不打击自由主义吗？》署1982年12月5日。李敖在这篇文字中延续《千秋万岁乌鸦求是合集》的政论、读书札记或杂文写作脉络，留下一个可定位的写作节点。",
    "view": [
      "写作线"
    ],
    "tags": [
      "千秋万岁乌鸦求是合集",
      "不打击自由主义吗？",
      "1982"
    ],
    "people": [
      "李敖"
    ],
    "places": [
      "台湾"
    ],
    "works": [
      "千秋万岁乌鸦求是合集",
      "不打击自由主义吗？"
    ],
    "certainty": "confirmed",
    "source": {
      "book": "千秋万岁乌鸦求是合集",
      "chapter": "033.不打击自由主义吗？",
      "path": "《大李敖全集5.0》（wjm_tcy版）分章节/003.惊世杂文类/013.千秋万岁乌鸦求是合集/033.不打击自由主义吗？.txt",
      "line": 105
    }
  },
  {
    "id": "qianqiu-wansui-1983-01-16-034-fikl5tg6ympdglq-hkgglppa3ffon6y",
    "date": "1983-01-16",
    "displayDate": "1983年1月16日夜，浴盆中作",
    "datePrecision": "day",
    "title": "李敖写《二次出狱后，声名翻两番》",
    "summary": "《二次出狱后，声名翻两番》署1983年1月16日夜，浴盆中作。李敖在这篇文字中延续《千秋万岁乌鸦求是合集》的政论、读书札记或杂文写作脉络，留下一个可定位的写作节点。",
    "view": [
      "写作线"
    ],
    "tags": [
      "千秋万岁乌鸦求是合集",
      "二次出狱后，声名翻两番",
      "1983"
    ],
    "people": [
      "李敖"
    ],
    "places": [
      "台湾"
    ],
    "works": [
      "千秋万岁乌鸦求是合集",
      "二次出狱后，声名翻两番"
    ],
    "certainty": "confirmed",
    "source": {
      "book": "千秋万岁乌鸦求是合集",
      "chapter": "034.二次出狱后，声名翻两番",
      "path": "《大李敖全集5.0》（wjm_tcy版）分章节/003.惊世杂文类/013.千秋万岁乌鸦求是合集/034.二次出狱后，声名翻两番.txt",
      "line": 63
    }
  },
  {
    "id": "qianqiu-wansui-1983-01-15-035-itvmd2k6nffufjufjukl8tm6u54",
    "date": "1983-01-15",
    "displayDate": "1983年1月15日",
    "datePrecision": "day",
    "title": "李敖写《当然是个人人格问题》",
    "summary": "《当然是个人人格问题》署1983年1月15日。李敖在这篇文字中延续《千秋万岁乌鸦求是合集》的政论、读书札记或杂文写作脉络，留下一个可定位的写作节点。",
    "view": [
      "写作线"
    ],
    "tags": [
      "千秋万岁乌鸦求是合集",
      "当然是个人人格问题",
      "1983"
    ],
    "people": [
      "李敖"
    ],
    "places": [
      "台湾"
    ],
    "works": [
      "千秋万岁乌鸦求是合集",
      "当然是个人人格问题"
    ],
    "certainty": "confirmed",
    "source": {
      "book": "千秋万岁乌鸦求是合集",
      "chapter": "035.当然是个人人格问题",
      "path": "《大李敖全集5.0》（wjm_tcy版）分章节/003.惊世杂文类/013.千秋万岁乌鸦求是合集/035.当然是个人人格问题.txt",
      "line": 19
    }
  },
  {
    "id": "qianqiu-wansui-1983-06-27-036-jddfl8j0bph9nijg6yfizfk0fgo",
    "date": "1983-06-27",
    "displayDate": "1983年6月27日",
    "datePrecision": "day",
    "title": "李敖写《我们总能看出些什么》",
    "summary": "《我们总能看出些什么》署1983年6月27日。李敖在这篇文字中延续《千秋万岁乌鸦求是合集》的政论、读书札记或杂文写作脉络，留下一个可定位的写作节点。",
    "view": [
      "写作线"
    ],
    "tags": [
      "千秋万岁乌鸦求是合集",
      "我们总能看出些什么",
      "1983"
    ],
    "people": [
      "李敖"
    ],
    "places": [
      "台湾"
    ],
    "works": [
      "千秋万岁乌鸦求是合集",
      "我们总能看出些什么"
    ],
    "certainty": "confirmed",
    "source": {
      "book": "千秋万岁乌鸦求是合集",
      "chapter": "036.我们总能看出些什么",
      "path": "《大李敖全集5.0》（wjm_tcy版）分章节/003.惊世杂文类/013.千秋万岁乌鸦求是合集/036.我们总能看出些什么.txt",
      "line": 115
    }
  },
  {
    "id": "qianqiu-wansui-1967-02-03-037-uc9lenjfci1wk1zfli",
    "date": "1967-02-03",
    "displayDate": "1967年2月3日，李敖亲具",
    "datePrecision": "day",
    "title": "李敖亲具《香江托孤文件》",
    "summary": "《香江托孤文件》文末写“1967年2月3日，李敖亲具”。李敖在文件中预设自己若在台湾被捕，嘱托王敬羲等人在香港、日本等地筹印其已发表及未发表著作，作为反共、反极权、反传统的托孤安排。",
    "view": [
      "写作线",
      "出版线",
      "政治线"
    ],
    "tags": [
      "千秋万岁乌鸦求是合集",
      "香江托孤文件",
      "1967",
      "香江托孤",
      "香港",
      "日本"
    ],
    "people": [
      "李敖",
      "王敬羲"
    ],
    "places": [
      "台湾",
      "香港",
      "日本"
    ],
    "works": [
      "千秋万岁乌鸦求是合集",
      "香江托孤文件"
    ],
    "certainty": "confirmed",
    "source": {
      "book": "千秋万岁乌鸦求是合集",
      "chapter": "037.香江托孤文件",
      "path": "《大李敖全集5.0》（wjm_tcy版）分章节/003.惊世杂文类/013.千秋万岁乌鸦求是合集/037.香江托孤文件.txt",
      "line": 21
    }
  },
  {
    "id": "qianqiu-wansui-1983-06-26-038-gjsfeoffuff1glkfocfgbfgppad",
    "date": "1983-06-26",
    "displayDate": "1983年6月26日",
    "datePrecision": "day",
    "title": "李敖写《又一个不合作主义者》",
    "summary": "《又一个不合作主义者》署1983年6月26日。李敖在这篇文字中延续《千秋万岁乌鸦求是合集》的政论、读书札记或杂文写作脉络，留下一个可定位的写作节点。",
    "view": [
      "写作线"
    ],
    "tags": [
      "千秋万岁乌鸦求是合集",
      "又一个不合作主义者",
      "1983"
    ],
    "people": [
      "李敖"
    ],
    "places": [
      "台湾"
    ],
    "works": [
      "千秋万岁乌鸦求是合集",
      "又一个不合作主义者"
    ],
    "certainty": "confirmed",
    "source": {
      "book": "千秋万岁乌鸦求是合集",
      "chapter": "038.又一个不合作主义者",
      "path": "《大李敖全集5.0》（wjm_tcy版）分章节/003.惊世杂文类/013.千秋万岁乌鸦求是合集/038.又一个不合作主义者.txt",
      "line": 13
    }
  },
  {
    "id": "qianqiu-wansui-1966-02-07-039-rnfffcglli6sfmonesj6nj5f",
    "date": "1966-02-07",
    "displayDate": "1966年2月7日",
    "datePrecision": "day",
    "title": "李敖写《读丘吉尔传的感想》",
    "summary": "《读丘吉尔传的感想》署1966年2月7日。李敖在这篇文字中延续《千秋万岁乌鸦求是合集》的政论、读书札记或杂文写作脉络，留下一个可定位的写作节点。",
    "view": [
      "写作线"
    ],
    "tags": [
      "千秋万岁乌鸦求是合集",
      "读丘吉尔传的感想",
      "1966"
    ],
    "people": [
      "李敖"
    ],
    "places": [
      "台湾"
    ],
    "works": [
      "千秋万岁乌鸦求是合集",
      "读丘吉尔传的感想"
    ],
    "certainty": "confirmed",
    "source": {
      "book": "千秋万岁乌鸦求是合集",
      "chapter": "039.读丘吉尔传的感想",
      "path": "《大李敖全集5.0》（wjm_tcy版）分章节/003.惊世杂文类/013.千秋万岁乌鸦求是合集/039.读丘吉尔传的感想.txt",
      "line": 15
    }
  },
  {
    "id": "qianqiu-wansui-1984-05-30-040-rlcffokdolzwi1jgl3nesq53foc",
    "date": "1984-05-30",
    "displayDate": "1984年5月30日",
    "datePrecision": "day",
    "title": "李敖写《记两本潜字号的著作》",
    "summary": "《记两本潜字号的著作》署1984年5月30日。李敖在这篇文字中延续《千秋万岁乌鸦求是合集》的政论、读书札记或杂文写作脉络，留下一个可定位的写作节点。",
    "view": [
      "写作线"
    ],
    "tags": [
      "千秋万岁乌鸦求是合集",
      "记两本潜字号的著作",
      "1984"
    ],
    "people": [
      "李敖"
    ],
    "places": [
      "台湾"
    ],
    "works": [
      "千秋万岁乌鸦求是合集",
      "记两本潜字号的著作"
    ],
    "certainty": "confirmed",
    "source": {
      "book": "千秋万岁乌鸦求是合集",
      "chapter": "040.记两本潜字号的著作",
      "path": "《大李敖全集5.0》（wjm_tcy版）分章节/003.惊世杂文类/013.千秋万岁乌鸦求是合集/040.记两本潜字号的著作.txt",
      "line": 23
    }
  },
  {
    "id": "qianqiu-wansui-1984-07-06-041-g1ro9xh5u-nesglqsifn9j",
    "date": "1984-07-06",
    "displayDate": "1984年7月6日晨",
    "datePrecision": "day",
    "title": "李敖写《“儿童团”的后遗症》",
    "summary": "《“儿童团”的后遗症》署1984年7月6日晨。李敖在这篇文字中延续《千秋万岁乌鸦求是合集》的政论、读书札记或杂文写作脉络，留下一个可定位的写作节点。",
    "view": [
      "写作线"
    ],
    "tags": [
      "千秋万岁乌鸦求是合集",
      "“儿童团”的后遗症",
      "1984"
    ],
    "people": [
      "李敖"
    ],
    "places": [
      "台湾"
    ],
    "works": [
      "千秋万岁乌鸦求是合集",
      "“儿童团”的后遗症"
    ],
    "certainty": "confirmed",
    "source": {
      "book": "千秋万岁乌鸦求是合集",
      "chapter": "041.“儿童团”的后遗症",
      "path": "《大李敖全集5.0》（wjm_tcy版）分章节/003.惊世杂文类/013.千秋万岁乌鸦求是合集/041.“儿童团”的后遗症.txt",
      "line": 53
    }
  },
  {
    "id": "qianqiu-wansui-1984-10-05-042-g3xg49fhtffai85i46lii",
    "date": "1984-10-05",
    "displayDate": "1984年10月5日",
    "datePrecision": "day",
    "title": "李敖写《再写乱世居家泪》",
    "summary": "《再写乱世居家泪》署1984年10月5日。李敖在这篇文字中延续《千秋万岁乌鸦求是合集》的政论、读书札记或杂文写作脉络，留下一个可定位的写作节点。",
    "view": [
      "写作线"
    ],
    "tags": [
      "千秋万岁乌鸦求是合集",
      "再写乱世居家泪",
      "1984"
    ],
    "people": [
      "李敖"
    ],
    "places": [
      "台湾"
    ],
    "works": [
      "千秋万岁乌鸦求是合集",
      "再写乱世居家泪"
    ],
    "certainty": "confirmed",
    "source": {
      "book": "千秋万岁乌鸦求是合集",
      "chapter": "042.再写乱世居家泪",
      "path": "《大李敖全集5.0》（wjm_tcy版）分章节/003.惊世杂文类/013.千秋万岁乌鸦求是合集/042.再写乱世居家泪.txt",
      "line": 33
    }
  },
  {
    "id": "qianqiu-wansui-1984-11-29-043-rnllkxptfrnlsifpnxpakik2",
    "date": "1984-11-29",
    "displayDate": "1984年11月29日晨5时",
    "datePrecision": "day",
    "title": "李敖写《谁流芳谁遗臭而已》",
    "summary": "《谁流芳谁遗臭而已》署1984年11月29日晨5时。李敖在这篇文字中延续《千秋万岁乌鸦求是合集》的政论、读书札记或杂文写作脉络，留下一个可定位的写作节点。",
    "view": [
      "写作线"
    ],
    "tags": [
      "千秋万岁乌鸦求是合集",
      "谁流芳谁遗臭而已",
      "1984"
    ],
    "people": [
      "李敖"
    ],
    "places": [
      "台湾"
    ],
    "works": [
      "千秋万岁乌鸦求是合集",
      "谁流芳谁遗臭而已"
    ],
    "certainty": "confirmed",
    "source": {
      "book": "千秋万岁乌鸦求是合集",
      "chapter": "043.谁流芳谁遗臭而已",
      "path": "《大李敖全集5.0》（wjm_tcy版）分章节/003.惊世杂文类/013.千秋万岁乌鸦求是合集/043.谁流芳谁遗臭而已.txt",
      "line": 25
    }
  },
  {
    "id": "qianqiu-wansui-1985-01-12-044-kcfpu7lh7ljfg49mnqi1c",
    "date": "1985-01-12",
    "displayDate": "1985年1月12日",
    "datePrecision": "day",
    "title": "李敖写《替苏治洋写状子》",
    "summary": "《替苏治洋写状子》署1985年1月12日。李敖在这篇文字中延续《千秋万岁乌鸦求是合集》的政论、读书札记或杂文写作脉络，留下一个可定位的写作节点。",
    "view": [
      "写作线",
      "法律线"
    ],
    "tags": [
      "千秋万岁乌鸦求是合集",
      "替苏治洋写状子",
      "1985",
      "苏治洋",
      "状子"
    ],
    "people": [
      "李敖",
      "苏治洋"
    ],
    "places": [
      "台湾"
    ],
    "works": [
      "千秋万岁乌鸦求是合集",
      "替苏治洋写状子"
    ],
    "certainty": "confirmed",
    "source": {
      "book": "千秋万岁乌鸦求是合集",
      "chapter": "044.替苏治洋写状子",
      "path": "《大李敖全集5.0》（wjm_tcy版）分章节/003.惊世杂文类/013.千秋万岁乌鸦求是合集/044.替苏治洋写状子.txt",
      "line": 37
    }
  },
  {
    "id": "qianqiu-wansui-1985-03-12-046-prjiwz-inqgk1n9j",
    "date": "1985-03-12",
    "displayDate": "1985年3月12日晨",
    "datePrecision": "day",
    "title": "李敖写《“良心”并发症》",
    "summary": "《“良心”并发症》署1985年3月12日晨。李敖在这篇文字中延续《千秋万岁乌鸦求是合集》的政论、读书札记或杂文写作脉络，留下一个可定位的写作节点。",
    "view": [
      "写作线"
    ],
    "tags": [
      "千秋万岁乌鸦求是合集",
      "“良心”并发症",
      "1985"
    ],
    "people": [
      "李敖"
    ],
    "places": [
      "台湾"
    ],
    "works": [
      "千秋万岁乌鸦求是合集",
      "“良心”并发症"
    ],
    "certainty": "confirmed",
    "source": {
      "book": "千秋万岁乌鸦求是合集",
      "chapter": "046.“良心”并发症",
      "path": "《大李敖全集5.0》（wjm_tcy版）分章节/003.惊世杂文类/013.千秋万岁乌鸦求是合集/046.“良心”并发症.txt",
      "line": 27
    }
  },
  {
    "id": "qianqiu-wansui-1984-05-07-047-k3hizrixsqzvg84g7lnesj6nj5f",
    "date": "1984-05-07",
    "displayDate": "1984年5月7日",
    "datePrecision": "day",
    "title": "李敖写《施性忠被判刑的感想》",
    "summary": "《施性忠被判刑的感想》署1984年5月7日。李敖在这篇文字中延续《千秋万岁乌鸦求是合集》的政论、读书札记或杂文写作脉络，留下一个可定位的写作节点。",
    "view": [
      "写作线"
    ],
    "tags": [
      "千秋万岁乌鸦求是合集",
      "施性忠被判刑的感想",
      "1984"
    ],
    "people": [
      "李敖"
    ],
    "places": [
      "台湾"
    ],
    "works": [
      "千秋万岁乌鸦求是合集",
      "施性忠被判刑的感想"
    ],
    "certainty": "confirmed",
    "source": {
      "book": "千秋万岁乌鸦求是合集",
      "chapter": "047.施性忠被判刑的感想",
      "path": "《大李敖全集5.0》（wjm_tcy版）分章节/003.惊世杂文类/013.千秋万岁乌鸦求是合集/047.施性忠被判刑的感想.txt",
      "line": 13
    }
  },
  {
    "id": "qianqiu-wansui-1985-01-09-049-glxh9gglpr9cgk1iwe",
    "date": "1985-01-09",
    "displayDate": "1985年1月9日午",
    "datePrecision": "day",
    "title": "李敖写《吕坤名言发微》",
    "summary": "《吕坤名言发微》署1985年1月9日午。李敖在这篇文字中延续《千秋万岁乌鸦求是合集》的政论、读书札记或杂文写作脉络，留下一个可定位的写作节点。",
    "view": [
      "写作线"
    ],
    "tags": [
      "千秋万岁乌鸦求是合集",
      "吕坤名言发微",
      "1985"
    ],
    "people": [
      "李敖"
    ],
    "places": [
      "台湾"
    ],
    "works": [
      "千秋万岁乌鸦求是合集",
      "吕坤名言发微"
    ],
    "certainty": "confirmed",
    "source": {
      "book": "千秋万岁乌鸦求是合集",
      "chapter": "049.吕坤名言发微",
      "path": "《大李敖全集5.0》（wjm_tcy版）分章节/003.惊世杂文类/013.千秋万岁乌鸦求是合集/049.吕坤名言发微.txt",
      "line": 13
    }
  },
  {
    "id": "qianqiu-wansui-1986-02-26-050-sf0lkxmko-kemk0mg2wts6-iof",
    "date": "1986-02-26",
    "displayDate": "1986年2月26日台北",
    "datePrecision": "day",
    "title": "李敖写远流版《李敖全集》序",
    "summary": "《远流版〈李敖全集〉序》文末署1986年2月26日台北。李敖为远流版《李敖全集》写序，回看“古典李敖”并说明重刊全集的意义。",
    "view": [
      "写作线",
      "出版线"
    ],
    "tags": [
      "千秋万岁乌鸦求是合集",
      "远流版《李敖全集》序",
      "1986"
    ],
    "people": [
      "李敖"
    ],
    "places": [
      "台北",
      "台湾"
    ],
    "works": [
      "千秋万岁乌鸦求是合集",
      "远流版《李敖全集》序",
      "李敖全集",
      "远流版李敖全集"
    ],
    "certainty": "confirmed",
    "source": {
      "book": "千秋万岁乌鸦求是合集",
      "chapter": "050.远流版《李敖全集》序",
      "path": "《大李敖全集5.0》（wjm_tcy版）分章节/003.惊世杂文类/013.千秋万岁乌鸦求是合集/050.远流版《李敖全集》序.txt",
      "line": 53
    }
  },
  {
    "id": "qianqiu-wansui-1981-12-31-054-rlmr3fhmimo2——g3grlmjzzlh7mnjk6np1ks6jpcc",
    "date": "1981-12-31",
    "displayDate": "1981年作",
    "datePrecision": "year",
    "title": "李敖写《论褫夺狂——兼论政治犯是终身职》",
    "summary": "《论褫夺狂——兼论政治犯是终身职》文末署1981年作。因原文只给年份，本轮以年级精度收为李敖关于政治犯与褫夺公权问题的写作节点。",
    "view": [
      "写作线",
      "政治线",
      "法律线"
    ],
    "tags": [
      "千秋万岁乌鸦求是合集",
      "论褫夺狂——兼论政治犯是终身职",
      "1981",
      "政治犯",
      "褫夺公权"
    ],
    "people": [
      "李敖"
    ],
    "places": [
      "台湾"
    ],
    "works": [
      "千秋万岁乌鸦求是合集",
      "论褫夺狂——兼论政治犯是终身职"
    ],
    "certainty": "contextual",
    "source": {
      "book": "千秋万岁乌鸦求是合集",
      "chapter": "054.论褫夺狂——兼论政治犯是终身职",
      "path": "《大李敖全集5.0》（wjm_tcy版）分章节/003.惊世杂文类/013.千秋万岁乌鸦求是合集/054.论褫夺狂——兼论政治犯是终身职.txt",
      "line": 127
    }
  },
  {
    "id": "qianqiu-wansui-1982-04-26-057-p21o2ui1pfl6g20n4vfeyfeorni",
    "date": "1982-04-26",
    "displayDate": "1982年4月26日",
    "datePrecision": "day",
    "title": "李敖写《给秦孝仪先生上一课》",
    "summary": "《给秦孝仪先生上一课》署1982年4月26日。李敖在这篇文字中延续《千秋万岁乌鸦求是合集》的政论、读书札记或杂文写作脉络，留下一个可定位的写作节点。",
    "view": [
      "写作线",
      "史料线"
    ],
    "tags": [
      "千秋万岁乌鸦求是合集",
      "给秦孝仪先生上一课",
      "1982",
      "秦孝仪"
    ],
    "people": [
      "李敖",
      "秦孝仪"
    ],
    "places": [
      "台湾"
    ],
    "works": [
      "千秋万岁乌鸦求是合集",
      "给秦孝仪先生上一课"
    ],
    "certainty": "confirmed",
    "source": {
      "book": "千秋万岁乌鸦求是合集",
      "chapter": "057.给秦孝仪先生上一课",
      "path": "《大李敖全集5.0》（wjm_tcy版）分章节/003.惊世杂文类/013.千秋万岁乌鸦求是合集/057.给秦孝仪先生上一课.txt",
      "line": 55
    }
  },
  {
    "id": "qianqiu-wansui-1982-07-24-058-r5rfkjfeogwsnesjh3rla",
    "date": "1982-07-24",
    "displayDate": "1982年7月24日",
    "datePrecision": "day",
    "title": "李敖写《西仓一喜的抗议》",
    "summary": "《西仓一喜的抗议》署1982年7月24日。李敖在这篇文字中延续《千秋万岁乌鸦求是合集》的政论、读书札记或杂文写作脉络，留下一个可定位的写作节点。",
    "view": [
      "写作线",
      "媒体线"
    ],
    "tags": [
      "千秋万岁乌鸦求是合集",
      "西仓一喜的抗议",
      "1982",
      "西仓一喜",
      "中央日报"
    ],
    "people": [
      "李敖",
      "西仓一喜"
    ],
    "places": [
      "台湾"
    ],
    "works": [
      "千秋万岁乌鸦求是合集",
      "西仓一喜的抗议",
      "中央日报"
    ],
    "certainty": "confirmed",
    "source": {
      "book": "千秋万岁乌鸦求是合集",
      "chapter": "058.西仓一喜的抗议",
      "path": "《大李敖全集5.0》（wjm_tcy版）分章节/003.惊世杂文类/013.千秋万岁乌鸦求是合集/058.西仓一喜的抗议.txt",
      "line": 43
    }
  },
  {
    "id": "qianqiu-wansui-1982-07-15-060-rlm-mavg53m7q",
    "date": "1982-07-15",
    "displayDate": "1982年7月15日",
    "datePrecision": "day",
    "title": "李敖写《论“烧冷灶”》",
    "summary": "《论“烧冷灶”》署1982年7月15日。李敖在这篇文字中延续《千秋万岁乌鸦求是合集》的政论、读书札记或杂文写作脉络，留下一个可定位的写作节点。",
    "view": [
      "写作线"
    ],
    "tags": [
      "千秋万岁乌鸦求是合集",
      "论“烧冷灶”",
      "1982"
    ],
    "people": [
      "李敖"
    ],
    "places": [
      "台湾"
    ],
    "works": [
      "千秋万岁乌鸦求是合集",
      "论“烧冷灶”"
    ],
    "certainty": "confirmed",
    "source": {
      "book": "千秋万岁乌鸦求是合集",
      "chapter": "060.论“烧冷灶”",
      "path": "《大李敖全集5.0》（wjm_tcy版）分章节/003.惊世杂文类/013.千秋万岁乌鸦求是合集/060.论“烧冷灶”.txt",
      "line": 17
    }
  },
  {
    "id": "qianqiu-wansui-1985-04-24-007-fifty-retreat-declaration",
    "date": "1985-04-24",
    "displayDate": "1985年五十生日前日",
    "datePrecision": "day",
    "title": "李敖写《五十闭关宣言》",
    "summary": "《坐五十·望一百》第一节《五十闭关宣言》署“一九八五年五十生日前日”。李敖以诗告老友，宣布五十以后“决心闭关”“不见朋友，只逛书摊”，把生命集中到写作上。",
    "view": [
      "写作线",
      "生活线"
    ],
    "tags": [
      "千秋万岁乌鸦求是合集",
      "坐五十·望一百",
      "五十闭关宣言",
      "闭关",
      "1985"
    ],
    "people": [
      "李敖"
    ],
    "places": [
      "台湾"
    ],
    "works": [
      "千秋万岁乌鸦求是合集",
      "坐五十·望一百",
      "五十闭关宣言"
    ],
    "certainty": "confirmed",
    "source": {
      "book": "千秋万岁乌鸦求是合集",
      "chapter": "007.坐五十·望一百",
      "path": "《大李敖全集5.0》（wjm_tcy版）分章节/003.惊世杂文类/013.千秋万岁乌鸦求是合集/007.坐五十·望一百.txt",
      "line": 23
    }
  },
  {
    "id": "qianqiu-wansui-1985-04-29-007-written-only-retreat-plan",
    "date": "1985-04-29",
    "displayDate": "1985年五十生日后四日",
    "datePrecision": "day",
    "title": "李敖说明闭关后只作书面交往",
    "summary": "《闭关宣言以后》署“一九八五年五十生日后四日”。李敖解释近三年“隐而不退”的试行经验，决定除非书面交往，其他“息交绝游”，并交代老友可投家中信箱、台北邮箱二六—七三五信箱，或送天元图书公司，由他以书面答复。",
    "view": [
      "生活线",
      "写作线"
    ],
    "tags": [
      "千秋万岁乌鸦求是合集",
      "坐五十·望一百",
      "闭关宣言以后",
      "息交绝游",
      "天元图书公司",
      "1985"
    ],
    "people": [
      "李敖"
    ],
    "places": [
      "台湾",
      "台北",
      "信义路四段一号水晶大厦十三楼"
    ],
    "works": [
      "千秋万岁乌鸦求是合集",
      "坐五十·望一百",
      "闭关宣言以后"
    ],
    "certainty": "confirmed",
    "source": {
      "book": "千秋万岁乌鸦求是合集",
      "chapter": "007.坐五十·望一百",
      "path": "《大李敖全集5.0》（wjm_tcy版）分章节/003.惊世杂文类/013.千秋万岁乌鸦求是合集/007.坐五十·望一百.txt",
      "line": 49
    }
  },
  {
    "id": "qianqiu-wansui-1980-03-21-012-hou-dejian-letter-to-li-ao",
    "date": "1980-03-21",
    "displayDate": "1980年3月21日",
    "datePrecision": "day",
    "title": "侯德健写长信给李敖请求二十万元援助",
    "summary": "《跋“侯德健给李敖的信”》说明侯德健在1980年3月、《龙的传人》发行前三星期写长信给李敖；信末署“晚 侯德健 白 69,3,21”。李敖后来发表此信，并记下收到后“哭笑不得”的反应。",
    "view": [
      "交往线",
      "文化线"
    ],
    "tags": [
      "千秋万岁乌鸦求是合集",
      "侯德健给李敖的信",
      "侯德健",
      "龙的传人",
      "1980"
    ],
    "people": [
      "李敖",
      "侯德健"
    ],
    "places": [
      "台湾"
    ],
    "works": [
      "千秋万岁乌鸦求是合集",
      "跋“侯德健给李敖的信”",
      "侯德健给李敖的信",
      "龙的传人"
    ],
    "certainty": "confirmed",
    "source": {
      "book": "千秋万岁乌鸦求是合集",
      "chapter": "012.跋“侯德健给李敖的信”",
      "path": "《大李敖全集5.0》（wjm_tcy版）分章节/003.惊世杂文类/013.千秋万岁乌鸦求是合集/012.跋“侯德健给李敖的信”.txt",
      "line": 73
    }
  },
  {
    "id": "qianqiu-wansui-1980-context-012-asks-xinge-raise-hou-dejian-income",
    "date": "1980-12-31",
    "displayDate": "1980年3月21日后、第二次入狱前",
    "datePrecision": "undated-context",
    "title": "李敖找新格唱片负责人替侯德健争取收入",
    "summary": "侯德健来信后，李敖自述自己没有二十万元可借，便找到新格唱片公司的负责人，询问能否设法提高侯德健从《龙的传人》唱片所得的收入，并要求不必向侯德健说明是他拜托；新格负责人答应试试看。",
    "view": [
      "交往线",
      "文化线"
    ],
    "tags": [
      "千秋万岁乌鸦求是合集",
      "侯德健",
      "新格唱片公司",
      "龙的传人",
      "义助",
      "1980"
    ],
    "people": [
      "李敖",
      "侯德健",
      "新格唱片公司负责人"
    ],
    "places": [
      "台湾"
    ],
    "works": [
      "千秋万岁乌鸦求是合集",
      "跋“侯德健给李敖的信”",
      "龙的传人"
    ],
    "certainty": "contextual",
    "source": {
      "book": "千秋万岁乌鸦求是合集",
      "chapter": "012.跋“侯德健给李敖的信”",
      "path": "《大李敖全集5.0》（wjm_tcy版）分章节/003.惊世杂文类/013.千秋万岁乌鸦求是合集/012.跋“侯德健给李敖的信”.txt",
      "line": 155
    }
  },
  {
    "id": "qianqiu-wansui-1982-context-012-asks-xinge-protest-song-chuyu-lyric-change",
    "date": "1982-12-31",
    "displayDate": "宋楚瑜窜改《龙的传人》后（1983年6月16日前）",
    "datePrecision": "undated-context",
    "title": "李敖要新格唱片向宋楚瑜抗议窜改《龙的传人》",
    "summary": "李敖在侯德健跋文中回忆，新闻局长宋楚瑜窜改《龙的传人》后，他很为侯德健不平，曾要求新格唱片公司向宋楚瑜抗议，但新格方面不敢。",
    "view": [
      "文化线",
      "政治线"
    ],
    "tags": [
      "千秋万岁乌鸦求是合集",
      "侯德健",
      "宋楚瑜",
      "新格唱片公司",
      "龙的传人",
      "1982"
    ],
    "people": [
      "李敖",
      "侯德健",
      "宋楚瑜",
      "新格唱片公司"
    ],
    "places": [
      "台湾"
    ],
    "works": [
      "千秋万岁乌鸦求是合集",
      "跋“侯德健给李敖的信”",
      "龙的传人"
    ],
    "certainty": "contextual",
    "source": {
      "book": "千秋万岁乌鸦求是合集",
      "chapter": "012.跋“侯德健给李敖的信”",
      "path": "《大李敖全集5.0》（wjm_tcy版）分章节/003.惊世杂文类/013.千秋万岁乌鸦求是合集/012.跋“侯德健给李敖的信”.txt",
      "line": 161
    }
  },
  {
    "id": "qianqiu-wansui-1983-06-16-012-writes-postscript-hou-dejian-letter",
    "date": "1983-06-16",
    "displayDate": "1983年6月16日",
    "datePrecision": "day",
    "title": "李敖写《跋“侯德健给李敖的信”》",
    "summary": "侯德健赴大陆后，李敖认为“该发表一封信、发表一些感想”，在1983年6月16日写成《跋“侯德健给李敖的信”》，公开侯德健1980年的来信，并回顾自己未能直接资助、转向找新格唱片帮忙等经过。",
    "view": [
      "写作线",
      "交往线",
      "文化线"
    ],
    "tags": [
      "千秋万岁乌鸦求是合集",
      "侯德健",
      "侯德健给李敖的信",
      "龙的传人",
      "1983"
    ],
    "people": [
      "李敖",
      "侯德健"
    ],
    "places": [
      "台湾"
    ],
    "works": [
      "千秋万岁乌鸦求是合集",
      "跋“侯德健给李敖的信”",
      "侯德健给李敖的信",
      "龙的传人"
    ],
    "certainty": "confirmed",
    "source": {
      "book": "千秋万岁乌鸦求是合集",
      "chapter": "012.跋“侯德健给李敖的信”",
      "path": "《大李敖全集5.0》（wjm_tcy版）分章节/003.惊世杂文类/013.千秋万岁乌鸦求是合集/012.跋“侯德健给李敖的信”.txt",
      "line": 187
    }
  },
  {
    "id": "qianqiu-wansui-1983-06-19-014-replies-lin-zhuoshui-nationalism",
    "date": "1983-06-19",
    "displayDate": "1983年6月19日（按本书相邻篇章语境锚定）",
    "datePrecision": "day-context",
    "title": "林浊水来信请李敖写民族观，李敖据《新夷说》回应",
    "summary": "《打倒冒牌的民族主义！》开头说林浊水六月十八日写信给李敖，请他表示中国人对“民族”的观念和运用等问题；李敖称“义不容辞”，仍据十八年前《新夷说》为基础重新申论。文末附林浊水催稿信，署“浊水 上 六月十九日”，并要求七月十五日前交卷。",
    "view": [
      "交往线",
      "写作线",
      "思想线"
    ],
    "tags": [
      "千秋万岁乌鸦求是合集",
      "打倒冒牌的民族主义",
      "林浊水",
      "新夷说",
      "民族主义",
      "1983"
    ],
    "people": [
      "李敖",
      "林浊水"
    ],
    "places": [
      "台湾"
    ],
    "works": [
      "千秋万岁乌鸦求是合集",
      "打倒冒牌的民族主义！",
      "新夷说"
    ],
    "certainty": "contextual",
    "source": {
      "book": "千秋万岁乌鸦求是合集",
      "chapter": "014.打倒冒牌的民族主义！",
      "path": "《大李敖全集5.0》（wjm_tcy版）分章节/003.惊世杂文类/013.千秋万岁乌鸦求是合集/014.打倒冒牌的民族主义！.txt",
      "line": 3
    }
  },
  {
    "id": "qianqiu-wansui-1971-04-16-055-finishes-happiness-law-in-prison",
    "date": "1971-04-16",
    "displayDate": "1971年4月16日写完",
    "datePrecision": "day",
    "title": "李敖在狱中写完《论“快乐律”》",
    "summary": "《论“快乐律”》文末署“1971年4月16日写完”，并附注说这是长编，“随手在狱里写的”，为了存真与纪念不再修饰。",
    "view": [
      "写作线",
      "狱中线",
      "思想线"
    ],
    "tags": [
      "千秋万岁乌鸦求是合集",
      "论“快乐律”",
      "狱中写作",
      "快乐律",
      "1971"
    ],
    "people": [
      "李敖"
    ],
    "places": [
      "台湾",
      "狱中"
    ],
    "works": [
      "千秋万岁乌鸦求是合集",
      "论“快乐律”"
    ],
    "certainty": "confirmed",
    "source": {
      "book": "千秋万岁乌鸦求是合集",
      "chapter": "055.论“快乐律”",
      "path": "《大李敖全集5.0》（wjm_tcy版）分章节/003.惊世杂文类/013.千秋万岁乌鸦求是合集/055.论“快乐律”.txt",
      "line": 29
    }
  },
  {
    "id": "qianqiu-wansui-1982-07-16-059-writes-on-deng-weizhen-talk",
    "date": "1982-07-16",
    "displayDate": "1982年7月16日",
    "datePrecision": "day",
    "title": "李敖写《注意邓维桢谈话》",
    "summary": "邓维桢七月接受于凡访问后，李敖读到谈话，写下四点感想，涉及老兵李师科、《深耕》查禁、徐复观与陶百川、黄信介与康宁祥等议题。本文文末署“一九八二年七月十六日”。",
    "view": [
      "写作线",
      "政治线",
      "媒体线"
    ],
    "tags": [
      "千秋万岁乌鸦求是合集",
      "注意邓维桢谈话",
      "邓维桢",
      "于凡",
      "李师科",
      "深耕",
      "1982"
    ],
    "people": [
      "李敖",
      "邓维桢",
      "于凡",
      "李师科",
      "康宁祥",
      "黄信介",
      "徐复观",
      "陶百川"
    ],
    "places": [
      "台湾"
    ],
    "works": [
      "千秋万岁乌鸦求是合集",
      "注意邓维桢谈话",
      "为老兵李师科喊话",
      "深耕"
    ],
    "certainty": "confirmed",
    "source": {
      "book": "千秋万岁乌鸦求是合集",
      "chapter": "059.注意邓维桢谈话",
      "path": "《大李敖全集5.0》（wjm_tcy版）分章节/003.惊世杂文类/013.千秋万岁乌鸦求是合集/059.注意邓维桢谈话.txt",
      "line": 55
    }
  },
  {
    "id": "qianqiu-wansui-1952-06-25-051-publishes-dewey-education-essay",
    "date": "1952-06-25",
    "displayDate": "1952年6月25日",
    "datePrecision": "day",
    "title": "李敖在《学生》发表《杜威的教育思想及其他》",
    "summary": "《李敖著作年表》记载，李敖高中二年级时，于1952年6月25日在《学生》杂志第四十六期发表《杜威的教育思想及其他》。",
    "view": [
      "写作线",
      "出版线"
    ],
    "tags": [
      "千秋万岁乌鸦求是合集",
      "李敖著作年表",
      "杜威的教育思想及其他",
      "学生杂志",
      "1952"
    ],
    "people": [
      "李敖"
    ],
    "places": [
      "台湾"
    ],
    "works": [
      "千秋万岁乌鸦求是合集",
      "李敖著作年表",
      "杜威的教育思想及其他",
      "学生"
    ],
    "certainty": "confirmed",
    "source": {
      "book": "千秋万岁乌鸦求是合集",
      "chapter": "051.李敖著作年表",
      "path": "《大李敖全集5.0》（wjm_tcy版）分章节/003.惊世杂文类/013.千秋万岁乌鸦求是合集/051.李敖著作年表.txt",
      "line": 39
    }
  },
  {
    "id": "qianqiu-wansui-1952-08-01-051-publishes-cooperation-and-capital-control",
    "date": "1952-08-01",
    "displayDate": "1952年8月1日",
    "datePrecision": "day",
    "title": "李敖发表《合作制度与节制资本》并获征文第一名",
    "summary": "《李敖著作年表》记载，李敖于1952年8月1日在《合作经济》第二卷第十二期发表《合作制度与节制资本》；此文参加庆祝第三十届国际合作节征文，得第一名，并让他拿到有生以来最大一笔奖金。",
    "view": [
      "写作线",
      "出版线"
    ],
    "tags": [
      "千秋万岁乌鸦求是合集",
      "李敖著作年表",
      "合作制度与节制资本",
      "合作经济",
      "征文",
      "1952"
    ],
    "people": [
      "李敖"
    ],
    "places": [
      "台湾"
    ],
    "works": [
      "千秋万岁乌鸦求是合集",
      "李敖著作年表",
      "合作制度与节制资本",
      "合作经济"
    ],
    "certainty": "confirmed",
    "source": {
      "book": "千秋万岁乌鸦求是合集",
      "chapter": "051.李敖著作年表",
      "path": "《大李敖全集5.0》（wjm_tcy版）分章节/003.惊世杂文类/013.千秋万岁乌鸦求是合集/051.李敖著作年表.txt",
      "line": 39
    }
  },
  {
    "id": "qianqiu-wansui-1955-11-15-051-publishes-reading-hu-shi-wencun-in-university-magazine",
    "date": "1955-11-15",
    "displayDate": "1955年11月15日、1956年1月1日",
    "datePrecision": "day-range",
    "title": "李敖中学旧作《读<胡适文存>》刊于《大学杂志》",
    "summary": "《李敖著作年表》记载，李敖大学一年级时，中学旧作《读<胡适文存>》刊于《大学杂志》第一卷第五、六期，期日为1955年11月15日与1956年1月1日。",
    "view": [
      "写作线",
      "出版线"
    ],
    "tags": [
      "千秋万岁乌鸦求是合集",
      "李敖著作年表",
      "读<胡适文存>",
      "大学杂志",
      "胡适",
      "1955",
      "1956"
    ],
    "people": [
      "李敖"
    ],
    "places": [
      "台湾"
    ],
    "works": [
      "千秋万岁乌鸦求是合集",
      "李敖著作年表",
      "读<胡适文存>",
      "大学杂志"
    ],
    "certainty": "confirmed",
    "source": {
      "book": "千秋万岁乌鸦求是合集",
      "chapter": "051.李敖著作年表",
      "path": "《大李敖全集5.0》（wjm_tcy版）分章节/003.惊世杂文类/013.千秋万岁乌鸦求是合集/051.李敖著作年表.txt",
      "line": 45
    }
  },
  {
    "id": "qianqiu-wansui-1957-03-01-051-publishes-from-reading-hu-shi-wencun",
    "date": "1957-03-01",
    "displayDate": "1957年3月1日",
    "datePrecision": "day",
    "title": "李敖在《自由中国》发表《从读<胡适文存>说起》",
    "summary": "《李敖著作年表》记载，李敖大学三年级时，于1957年3月1日在《自由中国》第十六卷第五期发表旧作《从读<胡适文存>说起》。",
    "view": [
      "写作线",
      "出版线"
    ],
    "tags": [
      "千秋万岁乌鸦求是合集",
      "李敖著作年表",
      "从读<胡适文存>说起",
      "自由中国",
      "胡适",
      "1957"
    ],
    "people": [
      "李敖"
    ],
    "places": [
      "台湾"
    ],
    "works": [
      "千秋万岁乌鸦求是合集",
      "李敖著作年表",
      "从读<胡适文存>说起",
      "自由中国"
    ],
    "certainty": "confirmed",
    "source": {
      "book": "千秋万岁乌鸦求是合集",
      "chapter": "051.李敖著作年表",
      "path": "《大李敖全集5.0》（wjm_tcy版）分章节/003.惊世杂文类/013.千秋万岁乌鸦求是合集/051.李敖著作年表.txt",
      "line": 49
    }
  },
  {
    "id": "qianqiu-wansui-1957-03-15-051-publishes-hu-shi-and-liang-qichao",
    "date": "1957-03-15",
    "displayDate": "1957年3月15日",
    "datePrecision": "day",
    "title": "李敖在《中央日报》副刊发表《胡适与梁启超》",
    "summary": "《李敖著作年表》记载，李敖于1957年3月15日在《中央日报》副刊发表《胡适与梁启超》。",
    "view": [
      "写作线",
      "出版线"
    ],
    "tags": [
      "千秋万岁乌鸦求是合集",
      "李敖著作年表",
      "胡适与梁启超",
      "中央日报",
      "胡适",
      "梁启超",
      "1957"
    ],
    "people": [
      "李敖"
    ],
    "places": [
      "台湾"
    ],
    "works": [
      "千秋万岁乌鸦求是合集",
      "李敖著作年表",
      "胡适与梁启超",
      "中央日报"
    ],
    "certainty": "confirmed",
    "source": {
      "book": "千秋万岁乌鸦求是合集",
      "chapter": "051.李敖著作年表",
      "path": "《大李敖全集5.0》（wjm_tcy版）分章节/003.惊世杂文类/013.千秋万岁乌鸦求是合集/051.李敖著作年表.txt",
      "line": 49
    }
  },
  {
    "id": "qianqiu-wansui-1957-04-05-051-publishes-hu-shi-and-xu-zhimo",
    "date": "1957-04-05",
    "displayDate": "1957年4月5日",
    "datePrecision": "day",
    "title": "李敖在《中央日报》副刊发表《胡适与徐志摩》",
    "summary": "《李敖著作年表》记载，李敖于1957年4月5日在《中央日报》副刊再发表《胡适与徐志摩》。",
    "view": [
      "写作线",
      "出版线"
    ],
    "tags": [
      "千秋万岁乌鸦求是合集",
      "李敖著作年表",
      "胡适与徐志摩",
      "中央日报",
      "胡适",
      "徐志摩",
      "1957"
    ],
    "people": [
      "李敖"
    ],
    "places": [
      "台湾"
    ],
    "works": [
      "千秋万岁乌鸦求是合集",
      "李敖著作年表",
      "胡适与徐志摩",
      "中央日报"
    ],
    "certainty": "confirmed",
    "source": {
      "book": "千秋万岁乌鸦求是合集",
      "chapter": "051.李敖著作年表",
      "path": "《大李敖全集5.0》（wjm_tcy版）分章节/003.惊世杂文类/013.千秋万岁乌鸦求是合集/051.李敖著作年表.txt",
      "line": 49
    }
  },
  {
    "id": "qianqiu-wansui-1958-02-15-051-publishes-on-luggage",
    "date": "1958-02-15",
    "displayDate": "1958年2月15日",
    "datePrecision": "day",
    "title": "李敖在《中央日报》副刊发表《关于行李》",
    "summary": "《李敖著作年表》记载，李敖大学四年级时，于1958年2月15日在《中央日报》副刊发表《关于行李》。",
    "view": [
      "写作线",
      "出版线"
    ],
    "tags": [
      "千秋万岁乌鸦求是合集",
      "李敖著作年表",
      "关于行李",
      "中央日报",
      "1958"
    ],
    "people": [
      "李敖"
    ],
    "places": [
      "台湾"
    ],
    "works": [
      "千秋万岁乌鸦求是合集",
      "李敖著作年表",
      "关于行李",
      "中央日报"
    ],
    "certainty": "confirmed",
    "source": {
      "book": "千秋万岁乌鸦求是合集",
      "chapter": "051.李敖著作年表",
      "path": "《大李敖全集5.0》（wjm_tcy版）分章节/003.惊世杂文类/013.千秋万岁乌鸦求是合集/051.李敖著作年表.txt",
      "line": 51
    }
  },
  {
    "id": "qianqiu-wansui-1958-06-08-051-starts-university-late-diary",
    "date": "1958-06-08",
    "displayDate": "1958年6月8日起",
    "datePrecision": "day",
    "title": "李敖起写《大学后期日记》",
    "summary": "《李敖著作年表》记载，李敖于1958年6月8日起写《大学后期日记》，此后留下大学后期生活、读书和交游记录。",
    "view": [
      "写作线",
      "出版线"
    ],
    "tags": [
      "千秋万岁乌鸦求是合集",
      "李敖著作年表",
      "大学后期日记",
      "日记",
      "1958"
    ],
    "people": [
      "李敖"
    ],
    "places": [
      "台湾"
    ],
    "works": [
      "千秋万岁乌鸦求是合集",
      "李敖著作年表",
      "大学后期日记"
    ],
    "certainty": "confirmed",
    "source": {
      "book": "千秋万岁乌鸦求是合集",
      "chapter": "051.李敖著作年表",
      "path": "《大李敖全集5.0》（wjm_tcy版）分章节/003.惊世杂文类/013.千秋万岁乌鸦求是合集/051.李敖著作年表.txt",
      "line": 51
    }
  },
  {
    "id": "qianqiu-wansui-1958-07-19-051-publishes-liang-qichao-and-xu-zhimo",
    "date": "1958-07-19",
    "displayDate": "1958年7月19日",
    "datePrecision": "day",
    "title": "李敖在《中央日报》副刊发表《梁启超与徐志摩》",
    "summary": "《李敖著作年表》记载，李敖于1958年7月19日在《中央日报》副刊再发表《梁启超与徐志摩》。",
    "view": [
      "写作线",
      "出版线"
    ],
    "tags": [
      "千秋万岁乌鸦求是合集",
      "李敖著作年表",
      "梁启超与徐志摩",
      "中央日报",
      "梁启超",
      "徐志摩",
      "1958"
    ],
    "people": [
      "李敖"
    ],
    "places": [
      "台湾"
    ],
    "works": [
      "千秋万岁乌鸦求是合集",
      "李敖著作年表",
      "梁启超与徐志摩",
      "中央日报"
    ],
    "certainty": "confirmed",
    "source": {
      "book": "千秋万岁乌鸦求是合集",
      "chapter": "051.李敖著作年表",
      "path": "《大李敖全集5.0》（wjm_tcy版）分章节/003.惊世杂文类/013.千秋万岁乌鸦求是合集/051.李敖著作年表.txt",
      "line": 51
    }
  },
  {
    "id": "qianqiu-wansui-1959-08-02-051-finishes-university-late-diary",
    "date": "1959-08-02",
    "displayDate": "1959年8月2日",
    "datePrecision": "day",
    "title": "李敖写完《大学后期日记》",
    "summary": "《李敖著作年表》记载，李敖1959年7月毕业，8月2日写完《大学后期日记》，随后赴凤山陆军步兵学校受第八期预备军官训练，并起写《一个预备军官的日记》。",
    "view": [
      "写作线",
      "出版线"
    ],
    "tags": [
      "千秋万岁乌鸦求是合集",
      "李敖著作年表",
      "大学后期日记",
      "日记",
      "预备军官",
      "1959"
    ],
    "people": [
      "李敖"
    ],
    "places": [
      "台湾",
      "凤山"
    ],
    "works": [
      "千秋万岁乌鸦求是合集",
      "李敖著作年表",
      "大学后期日记",
      "一个预备军官的日记"
    ],
    "certainty": "confirmed",
    "source": {
      "book": "千秋万岁乌鸦求是合集",
      "chapter": "051.李敖著作年表",
      "path": "《大李敖全集5.0》（wjm_tcy版）分章节/003.惊世杂文类/013.千秋万岁乌鸦求是合集/051.李敖著作年表.txt",
      "line": 53
    }
  },
  {
    "id": "qianqiu-wansui-1964-01-25-051-publishes-history-and-portraits",
    "date": "1964-01-25",
    "displayDate": "1964年1月25日",
    "datePrecision": "day",
    "title": "李敖出版《历史与人像》",
    "summary": "《李敖著作年表》记载，李敖于1964年1月25日出版《历史与人像》，并在书目中注明此书后来遭查禁。",
    "view": [
      "写作线",
      "出版线"
    ],
    "tags": [
      "千秋万岁乌鸦求是合集",
      "李敖著作年表",
      "历史与人像",
      "查禁",
      "1964"
    ],
    "people": [
      "李敖"
    ],
    "places": [
      "台湾"
    ],
    "works": [
      "千秋万岁乌鸦求是合集",
      "李敖著作年表",
      "历史与人像"
    ],
    "certainty": "confirmed",
    "crossReferences": [
      "1966-books-banned"
    ],
    "source": {
      "book": "千秋万岁乌鸦求是合集",
      "chapter": "051.李敖著作年表",
      "path": "《大李敖全集5.0》（wjm_tcy版）分章节/003.惊世杂文类/013.千秋万岁乌鸦求是合集/051.李敖著作年表.txt",
      "line": 63
    }
  },
  {
    "id": "qianqiu-wansui-1964-03-25-051-publishes-hu-shi-research",
    "date": "1964-03-25",
    "displayDate": "1964年3月25日",
    "datePrecision": "day",
    "title": "李敖出版《胡适研究》",
    "summary": "《李敖著作年表》记载，李敖于1964年3月25日出版《胡适研究》，这是其胡适研究书系中的早期单行本之一。",
    "view": [
      "写作线",
      "出版线"
    ],
    "tags": [
      "千秋万岁乌鸦求是合集",
      "李敖著作年表",
      "胡适研究",
      "胡适",
      "1964"
    ],
    "people": [
      "李敖"
    ],
    "places": [
      "台湾"
    ],
    "works": [
      "千秋万岁乌鸦求是合集",
      "李敖著作年表",
      "胡适研究"
    ],
    "certainty": "confirmed",
    "source": {
      "book": "千秋万岁乌鸦求是合集",
      "chapter": "051.李敖著作年表",
      "path": "《大李敖全集5.0》（wjm_tcy版）分章节/003.惊世杂文类/013.千秋万岁乌鸦求是合集/051.李敖著作年表.txt",
      "line": 63
    }
  },
  {
    "id": "qianqiu-wansui-1964-04-10-051-publishes-hu-shi-critical-biography",
    "date": "1964-04-10",
    "displayDate": "1964年4月10日",
    "datePrecision": "day",
    "title": "李敖出版《胡适评传》",
    "summary": "《李敖著作年表》记载，李敖于1964年4月10日出版《胡适评传》；此书后来引发陶希圣《谤书》等攻击。",
    "view": [
      "写作线",
      "出版线"
    ],
    "tags": [
      "千秋万岁乌鸦求是合集",
      "李敖著作年表",
      "胡适评传",
      "胡适",
      "陶希圣",
      "1964"
    ],
    "people": [
      "李敖"
    ],
    "places": [
      "台湾"
    ],
    "works": [
      "千秋万岁乌鸦求是合集",
      "李敖著作年表",
      "胡适评传"
    ],
    "certainty": "confirmed",
    "crossReferences": [
      "1964-09-06-tao-bangshu",
      "book7-1964-09-06-tao-xisheng-publishes-bangshu-attacking-hu-shi-pingzhuan"
    ],
    "source": {
      "book": "千秋万岁乌鸦求是合集",
      "chapter": "051.李敖著作年表",
      "path": "《大李敖全集5.0》（wjm_tcy版）分章节/003.惊世杂文类/013.千秋万岁乌鸦求是合集/051.李敖著作年表.txt",
      "line": 63
    }
  },
  {
    "id": "qianqiu-wansui-1964-06-25-051-publishes-thought-trend-answer",
    "date": "1964-06-25",
    "displayDate": "1964年6月25日",
    "datePrecision": "day",
    "title": "李敖出版《为中国思想趋向求答案》",
    "summary": "《李敖著作年表》记载，李敖于1964年6月25日出版《为中国思想趋向求答案》，并注明此书后来遭查禁。",
    "view": [
      "写作线",
      "出版线"
    ],
    "tags": [
      "千秋万岁乌鸦求是合集",
      "李敖著作年表",
      "为中国思想趋向求答案",
      "查禁",
      "1964"
    ],
    "people": [
      "李敖"
    ],
    "places": [
      "台湾"
    ],
    "works": [
      "千秋万岁乌鸦求是合集",
      "李敖著作年表",
      "为中国思想趋向求答案"
    ],
    "certainty": "confirmed",
    "source": {
      "book": "千秋万岁乌鸦求是合集",
      "chapter": "051.李敖著作年表",
      "path": "《大李敖全集5.0》（wjm_tcy版）分章节/003.惊世杂文类/013.千秋万岁乌鸦求是合集/051.李敖著作年表.txt",
      "line": 63
    }
  },
  {
    "id": "qianqiu-wansui-1964-07-25-051-publishes-cultural-debate-danhuo",
    "date": "1964-07-25",
    "displayDate": "1964年7月25日",
    "datePrecision": "day",
    "title": "李敖出版《文化论战丹火录》",
    "summary": "《李敖著作年表》记载，李敖于1964年7月25日出版《文化论战丹火录》，并注明此书后来遭查禁。",
    "view": [
      "写作线",
      "出版线"
    ],
    "tags": [
      "千秋万岁乌鸦求是合集",
      "李敖著作年表",
      "文化论战丹火录",
      "查禁",
      "1964"
    ],
    "people": [
      "李敖"
    ],
    "places": [
      "台湾"
    ],
    "works": [
      "千秋万岁乌鸦求是合集",
      "李敖著作年表",
      "文化论战丹火录"
    ],
    "certainty": "confirmed",
    "source": {
      "book": "千秋万岁乌鸦求是合集",
      "chapter": "051.李敖著作年表",
      "path": "《大李敖全集5.0》（wjm_tcy版）分章节/003.惊世杂文类/013.千秋万岁乌鸦求是合集/051.李敖著作年表.txt",
      "line": 63
    }
  },
  {
    "id": "qianqiu-wansui-1964-08-25-051-publishes-education-and-faces",
    "date": "1964-08-25",
    "displayDate": "1964年8月25日",
    "datePrecision": "day",
    "title": "李敖出版《教育与脸谱》",
    "summary": "《李敖著作年表》记载，李敖于1964年8月25日出版《教育与脸谱》，并注明此书后来遭查禁。",
    "view": [
      "写作线",
      "出版线"
    ],
    "tags": [
      "千秋万岁乌鸦求是合集",
      "李敖著作年表",
      "教育与脸谱",
      "查禁",
      "1964"
    ],
    "people": [
      "李敖"
    ],
    "places": [
      "台湾"
    ],
    "works": [
      "千秋万岁乌鸦求是合集",
      "李敖著作年表",
      "教育与脸谱"
    ],
    "certainty": "confirmed",
    "source": {
      "book": "千秋万岁乌鸦求是合集",
      "chapter": "051.李敖著作年表",
      "path": "《大李敖全集5.0》（wjm_tcy版）分章节/003.惊世杂文类/013.千秋万岁乌鸦求是合集/051.李敖著作年表.txt",
      "line": 63
    }
  },
  {
    "id": "qianqiu-wansui-1965-09-25-051-publishes-shangxia-gujin-talks",
    "date": "1965-09-25",
    "displayDate": "1965年9月25日",
    "datePrecision": "day",
    "title": "李敖出版《上下古今谈》",
    "summary": "《李敖著作年表》记载，李敖于1965年9月25日出版《上下古今谈》，并注明此书后来遭查禁。",
    "view": [
      "写作线",
      "出版线"
    ],
    "tags": [
      "千秋万岁乌鸦求是合集",
      "李敖著作年表",
      "上下古今谈",
      "查禁",
      "1965"
    ],
    "people": [
      "李敖"
    ],
    "places": [
      "台湾"
    ],
    "works": [
      "千秋万岁乌鸦求是合集",
      "李敖著作年表",
      "上下古今谈"
    ],
    "certainty": "confirmed",
    "source": {
      "book": "千秋万岁乌鸦求是合集",
      "chapter": "051.李敖著作年表",
      "path": "《大李敖全集5.0》（wjm_tcy版）分章节/003.惊世杂文类/013.千秋万岁乌鸦求是合集/051.李敖著作年表.txt",
      "line": 65
    }
  },
  {
    "id": "qianqiu-wansui-1965-09-25-051-publishes-minbian-and-wenxing-lawsuit",
    "date": "1965-09-25",
    "displayDate": "1965年9月25日",
    "datePrecision": "day",
    "title": "李敖出版《闽变研究与文星讼案》",
    "summary": "《李敖著作年表》记载，李敖于1965年9月25日同日出版《闽变研究与文星讼案》，并注明此书后来遭查禁。",
    "view": [
      "写作线",
      "出版线"
    ],
    "tags": [
      "千秋万岁乌鸦求是合集",
      "李敖著作年表",
      "闽变研究与文星讼案",
      "文星讼案",
      "查禁",
      "1965"
    ],
    "people": [
      "李敖"
    ],
    "places": [
      "台湾"
    ],
    "works": [
      "千秋万岁乌鸦求是合集",
      "李敖著作年表",
      "闽变研究与文星讼案"
    ],
    "certainty": "confirmed",
    "source": {
      "book": "千秋万岁乌鸦求是合集",
      "chapter": "051.李敖著作年表",
      "path": "《大李敖全集5.0》（wjm_tcy版）分章节/003.惊世杂文类/013.千秋万岁乌鸦求是合集/051.李敖著作年表.txt",
      "line": 65
    }
  },
  {
    "id": "qianqiu-wansui-1965-11-12-051-publishes-sun-yatsen-western-medicine",
    "date": "1965-11-12",
    "displayDate": "1965年11月12日",
    "datePrecision": "day",
    "title": "李敖出版《孙逸仙和中国西化医学》",
    "summary": "《李敖著作年表》记载，李敖于1965年11月12日出版《孙逸仙和中国西化医学》，并注明此书后来遭查禁。旧库已有年份级写作/查禁节点，本条补出出版日。",
    "view": [
      "写作线",
      "出版线"
    ],
    "tags": [
      "千秋万岁乌鸦求是合集",
      "李敖著作年表",
      "孙逸仙和中国西化医学",
      "孙逸仙",
      "中国西化医学",
      "查禁",
      "1965"
    ],
    "people": [
      "李敖"
    ],
    "places": [
      "台湾"
    ],
    "works": [
      "千秋万岁乌鸦求是合集",
      "李敖著作年表",
      "孙逸仙和中国西化医学"
    ],
    "certainty": "confirmed",
    "crossReferences": [
      "book5-1965-writes-sun-yatsen-western-medicine",
      "1966-books-banned"
    ],
    "source": {
      "book": "千秋万岁乌鸦求是合集",
      "chapter": "051.李敖著作年表",
      "path": "《大李敖全集5.0》（wjm_tcy版）分章节/003.惊世杂文类/013.千秋万岁乌鸦求是合集/051.李敖著作年表.txt",
      "line": 65
    }
  },
  {
    "id": "qianqiu-wansui-1966-11-05-051-publishes-farewell-literary-world-ten-books",
    "date": "1966-11-05",
    "displayDate": "1966年11月5日",
    "datePrecision": "day",
    "title": "李敖出版《李敖告别文坛十书》",
    "summary": "《李敖著作年表》记载，李敖于1966年11月5日出版《李敖告别文坛十书》，其中《乌鸦又叫了》《两性问题及其他》《李敖写的信》《也有情书》《孙悟空和我》《不要叫罢》等遭查禁或在装订厂被没收，部分书册则被扣留、勒令割页后出厂。",
    "view": [
      "写作线",
      "出版线"
    ],
    "tags": [
      "千秋万岁乌鸦求是合集",
      "李敖著作年表",
      "李敖告别文坛十书",
      "乌鸦又叫了",
      "两性问题及其他",
      "李敖写的信",
      "也有情书",
      "孙悟空和我",
      "查禁",
      "1966"
    ],
    "people": [
      "李敖"
    ],
    "places": [
      "台湾"
    ],
    "works": [
      "千秋万岁乌鸦求是合集",
      "李敖著作年表",
      "李敖告别文坛十书",
      "乌鸦又叫了",
      "两性问题及其他",
      "妈离不了你",
      "李敖写的信",
      "也有情书",
      "传统下的再白",
      "孙悟空和我",
      "大学后期日记甲集",
      "大学后期日记乙集",
      "不要叫罢"
    ],
    "certainty": "confirmed",
    "crossReferences": [
      "book7-1966-11-09-books-seized-at-yajiang-binding-factory",
      "1965-11-05-ten-books-seized"
    ],
    "source": {
      "book": "千秋万岁乌鸦求是合集",
      "chapter": "051.李敖著作年表",
      "path": "《大李敖全集5.0》（wjm_tcy版）分章节/003.惊世杂文类/013.千秋万岁乌鸦求是合集/051.李敖著作年表.txt",
      "line": 67
    }
  },
  {
    "id": "qianqiu-wansui-1971-051-jiegubufengjin-published-in-hongkong",
    "date": "1971-12-31",
    "displayDate": "1971年",
    "datePrecision": "year",
    "title": "《借古不讽今》在香港出版",
    "summary": "《李敖著作年表》记载，李敖1971年被捕下狱前后，《借古不讽今》在香港出版，台湾不准进口。旧库已有王敬羲在香港刊出此书且未付版税的回忆线，本条补入本年表的出版归档。",
    "view": [
      "写作线",
      "出版线"
    ],
    "tags": [
      "千秋万岁乌鸦求是合集",
      "李敖著作年表",
      "借古不讽今",
      "香港出版",
      "台湾不准进口",
      "1971"
    ],
    "people": [
      "李敖"
    ],
    "places": [
      "香港",
      "台湾"
    ],
    "works": [
      "千秋万岁乌鸦求是合集",
      "李敖著作年表",
      "借古不讽今"
    ],
    "certainty": "confirmed",
    "crossReferences": [
      "book5-1966-wang-jingxi-hongkong-publishes-jiegubufengjin-no-royalties"
    ],
    "source": {
      "book": "千秋万岁乌鸦求是合集",
      "chapter": "051.李敖著作年表",
      "path": "《大李敖全集5.0》（wjm_tcy版）分章节/003.惊世杂文类/013.千秋万岁乌鸦求是合集/051.李敖著作年表.txt",
      "line": 77
    }
  },
  {
    "id": "qianqiu-wansui-1979-09-15-051-publishes-wencun-and-wencun-two",
    "date": "1979-09-15",
    "displayDate": "1979年9月15日",
    "datePrecision": "day",
    "title": "李敖出版《李敖文存》《李敖文存二集》",
    "summary": "《李敖著作年表》记载，李敖1979年6月复出后，于9月15日出版《李敖文存》和《李敖文存二集》。旧库已有两书内大量单篇写作与发表节点，本条补出两部书的同日出版层。",
    "view": [
      "写作线",
      "出版线"
    ],
    "tags": [
      "千秋万岁乌鸦求是合集",
      "李敖著作年表",
      "李敖文存",
      "李敖文存二集",
      "复出",
      "1979"
    ],
    "people": [
      "李敖"
    ],
    "places": [
      "台湾"
    ],
    "works": [
      "千秋万岁乌鸦求是合集",
      "李敖著作年表",
      "李敖文存",
      "李敖文存二集"
    ],
    "certainty": "confirmed",
    "source": {
      "book": "千秋万岁乌鸦求是合集",
      "chapter": "051.李敖著作年表",
      "path": "《大李敖全集5.0》（wjm_tcy版）分章节/003.惊世杂文类/013.千秋万岁乌鸦求是合集/051.李敖著作年表.txt",
      "line": 93
    }
  },
  {
    "id": "qianqiu-wansui-1982-06-051-publishes-three-emotion-books",
    "date": "1982-06-30",
    "displayDate": "1982年6月",
    "datePrecision": "month",
    "title": "李敖出版《三情之书》三种",
    "summary": "《李敖著作年表》记载，李敖1982年6月又出版《三情之书》：《李敖的情诗》《李敖的情书》《李敖的情话》。",
    "view": [
      "写作线",
      "出版线"
    ],
    "tags": [
      "千秋万岁乌鸦求是合集",
      "李敖著作年表",
      "三情之书",
      "李敖的情诗",
      "李敖的情书",
      "李敖的情话",
      "1982"
    ],
    "people": [
      "李敖"
    ],
    "places": [
      "台湾"
    ],
    "works": [
      "千秋万岁乌鸦求是合集",
      "李敖著作年表",
      "三情之书",
      "李敖的情诗",
      "李敖的情书",
      "李敖的情话"
    ],
    "certainty": "confirmed",
    "source": {
      "book": "千秋万岁乌鸦求是合集",
      "chapter": "051.李敖著作年表",
      "path": "《大李敖全集5.0》（wjm_tcy版）分章节/003.惊世杂文类/013.千秋万岁乌鸦求是合集/051.李敖著作年表.txt",
      "line": 99
    }
  },
  {
    "id": "qianqiu-wansui-1983-08-25-051-publishes-qianqiu-review-extra-1",
    "date": "1983-08-25",
    "displayDate": "1983年8月25日",
    "datePrecision": "day",
    "title": "李敖出版《李敖千秋评论号外》第一期",
    "summary": "《李敖著作年表》记载，李敖于1983年8月25日出版《李敖千秋评论号外》第一期《千秋评论号外》。",
    "view": [
      "写作线",
      "出版线"
    ],
    "tags": [
      "千秋万岁乌鸦求是合集",
      "李敖著作年表",
      "李敖千秋评论号外",
      "千秋评论号外",
      "千秋评论",
      "1983"
    ],
    "people": [
      "李敖"
    ],
    "places": [
      "台湾"
    ],
    "works": [
      "千秋万岁乌鸦求是合集",
      "李敖著作年表",
      "李敖千秋评论号外",
      "千秋评论号外"
    ],
    "certainty": "confirmed",
    "source": {
      "book": "千秋万岁乌鸦求是合集",
      "chapter": "051.李敖著作年表",
      "path": "《大李敖全集5.0》（wjm_tcy版）分章节/003.惊世杂文类/013.千秋万岁乌鸦求是合集/051.李敖著作年表.txt",
      "line": 101
    }
  },
  {
    "id": "qianqiu-wansui-1983-11-10-051-publishes-battle-is-test-of-dangwai",
    "date": "1983-11-10",
    "displayDate": "1983年11月10日",
    "datePrecision": "day",
    "title": "李敖出版《战斗是检验党外的唯一标准》",
    "summary": "《李敖著作年表》记载，李敖于1983年11月10日出版《战斗是检验党外的唯一标准》。",
    "view": [
      "写作线",
      "出版线"
    ],
    "tags": [
      "千秋万岁乌鸦求是合集",
      "李敖著作年表",
      "战斗是检验党外的唯一标准",
      "党外",
      "1983"
    ],
    "people": [
      "李敖"
    ],
    "places": [
      "台湾"
    ],
    "works": [
      "千秋万岁乌鸦求是合集",
      "李敖著作年表",
      "战斗是检验党外的唯一标准"
    ],
    "certainty": "confirmed",
    "source": {
      "book": "千秋万岁乌鸦求是合集",
      "chapter": "051.李敖著作年表",
      "path": "《大李敖全集5.0》（wjm_tcy版）分章节/003.惊世杂文类/013.千秋万岁乌鸦求是合集/051.李敖著作年表.txt",
      "line": 101
    }
  },
  {
    "id": "qianqiu-wansui-1983-11-20-051-publishes-qianqiu-review-extra-2",
    "date": "1983-11-20",
    "displayDate": "1983年11月20日",
    "datePrecision": "day",
    "title": "李敖出版《李敖千秋评论号外》第二期《开枪·斗牛·蛋》",
    "summary": "《李敖著作年表》记载，李敖于1983年11月20日出版《李敖千秋评论号外》第二期《开枪·斗牛·蛋》。",
    "view": [
      "写作线",
      "出版线"
    ],
    "tags": [
      "千秋万岁乌鸦求是合集",
      "李敖著作年表",
      "李敖千秋评论号外",
      "开枪·斗牛·蛋",
      "千秋评论",
      "1983"
    ],
    "people": [
      "李敖"
    ],
    "places": [
      "台湾"
    ],
    "works": [
      "千秋万岁乌鸦求是合集",
      "李敖著作年表",
      "李敖千秋评论号外",
      "开枪·斗牛·蛋"
    ],
    "certainty": "confirmed",
    "source": {
      "book": "千秋万岁乌鸦求是合集",
      "chapter": "051.李敖著作年表",
      "path": "《大李敖全集5.0》（wjm_tcy版）分章节/003.惊世杂文类/013.千秋万岁乌鸦求是合集/051.李敖著作年表.txt",
      "line": 101
    }
  },
  {
    "id": "qianqiu-wansui-1983-11-30-051-publishes-qianqiu-review-extra-3",
    "date": "1983-11-30",
    "displayDate": "1983年11月30日",
    "datePrecision": "day",
    "title": "李敖出版《李敖千秋评论号外》第三期《鸡骨·泡沫·抢》",
    "summary": "《李敖著作年表》记载，李敖于1983年11月30日出版《李敖千秋评论号外》第三期《鸡骨·泡沫·抢》。",
    "view": [
      "写作线",
      "出版线"
    ],
    "tags": [
      "千秋万岁乌鸦求是合集",
      "李敖著作年表",
      "李敖千秋评论号外",
      "鸡骨·泡沫·抢",
      "千秋评论",
      "1983"
    ],
    "people": [
      "李敖"
    ],
    "places": [
      "台湾"
    ],
    "works": [
      "千秋万岁乌鸦求是合集",
      "李敖著作年表",
      "李敖千秋评论号外",
      "鸡骨·泡沫·抢"
    ],
    "certainty": "confirmed",
    "source": {
      "book": "千秋万岁乌鸦求是合集",
      "chapter": "051.李敖著作年表",
      "path": "《大李敖全集5.0》（wjm_tcy版）分章节/003.惊世杂文类/013.千秋万岁乌鸦求是合集/051.李敖著作年表.txt",
      "line": 101
    }
  },
  {
    "id": "qianqiu-wansui-1984-04-15-051-publishes-qianqiu-review-extra-4",
    "date": "1984-04-15",
    "displayDate": "1984年4月15日",
    "datePrecision": "day",
    "title": "李敖出版《李敖千秋评论号外》第四期《公论·私通·我》",
    "summary": "《李敖著作年表》记载，李敖于1984年4月15日出版《李敖千秋评论号外》第四期《公论·私通·我》。",
    "view": [
      "写作线",
      "出版线"
    ],
    "tags": [
      "千秋万岁乌鸦求是合集",
      "李敖著作年表",
      "李敖千秋评论号外",
      "公论·私通·我",
      "千秋评论",
      "1984"
    ],
    "people": [
      "李敖"
    ],
    "places": [
      "台湾"
    ],
    "works": [
      "千秋万岁乌鸦求是合集",
      "李敖著作年表",
      "李敖千秋评论号外",
      "公论·私通·我"
    ],
    "certainty": "confirmed",
    "source": {
      "book": "千秋万岁乌鸦求是合集",
      "chapter": "051.李敖著作年表",
      "path": "《大李敖全集5.0》（wjm_tcy版）分章节/003.惊世杂文类/013.千秋万岁乌鸦求是合集/051.李敖著作年表.txt",
      "line": 103
    }
  },
  {
    "id": "qianqiu-wansui-1985-03-01-051-publishes-jinzhen-duyuren",
    "date": "1985-03-01",
    "displayDate": "1985年3月1日",
    "datePrecision": "day",
    "title": "李敖出版《要把金针度与人》",
    "summary": "《李敖著作年表》记载，李敖于1985年3月1日出版《要把金针度与人》。",
    "view": [
      "写作线",
      "出版线"
    ],
    "tags": [
      "千秋万岁乌鸦求是合集",
      "李敖著作年表",
      "要把金针度与人",
      "1985"
    ],
    "people": [
      "李敖"
    ],
    "places": [
      "台湾"
    ],
    "works": [
      "千秋万岁乌鸦求是合集",
      "李敖著作年表",
      "要把金针度与人"
    ],
    "certainty": "confirmed",
    "source": {
      "book": "千秋万岁乌鸦求是合集",
      "chapter": "051.李敖著作年表",
      "path": "《大李敖全集5.0》（wjm_tcy版）分章节/003.惊世杂文类/013.千秋万岁乌鸦求是合集/051.李敖著作年表.txt",
      "line": 105
    }
  },
  {
    "id": "qianqiu-wansui-1985-08-30-051-publishes-good-cat",
    "date": "1985-08-30",
    "displayDate": "1985年8月30日",
    "datePrecision": "day",
    "title": "李敖出版《能下床就是好猫》",
    "summary": "《李敖著作年表》记载，李敖于1985年8月30日出版《能下床就是好猫》。旧库已有1984年2月12日同题文字写作节点，本条补出成书出版层。",
    "view": [
      "写作线",
      "出版线"
    ],
    "tags": [
      "千秋万岁乌鸦求是合集",
      "李敖著作年表",
      "能下床就是好猫",
      "1985"
    ],
    "people": [
      "李敖"
    ],
    "places": [
      "台湾"
    ],
    "works": [
      "千秋万岁乌鸦求是合集",
      "李敖著作年表",
      "能下床就是好猫"
    ],
    "certainty": "confirmed",
    "crossReferences": [
      "bobo-song-1984-02-12-good-cat"
    ],
    "source": {
      "book": "千秋万岁乌鸦求是合集",
      "chapter": "051.李敖著作年表",
      "path": "《大李敖全集5.0》（wjm_tcy版）分章节/003.惊世杂文类/013.千秋万岁乌鸦求是合集/051.李敖著作年表.txt",
      "line": 105
    }
  }
]
